[
  {
    "ID": 0,
    "Mass": 1989100,
    "Name": "Black_hole",
    "Pos": [
      0.0,
      0.0,
      0.0
    ],
    "Radius": 100
  },
  {
    "ID": 1,
    "Mass": 4.522,
    "Name": "K0083N",
    "Pos": [
      28018031963.0,
      82450706583.0,
      0.0
    ],
    "Radius": 12
  },
  {
    "ID": 2,
    "Mass": 6.0495,
    "Name": "G8HFV1",
    "Pos": [
      -83771325281.0,
      4314154507.0,
      0.0
    ],
    "Radius": 19
  },
  {
    "ID": 3,
    "Mass": 9.0029,
    "Name": "QCKNST",
    "Pos": [
      51403356924.0,
      -21210479935.0,
      0.0
    ],
    "Radius": 18
  },
  {
    "ID": 4,
    "Mass": 4.9926,
    "Name": "SK0AVB",
    "Pos": [
      78328512358.0,
      90871438724.0,
      0.0
    ],
    "Radius": 11
  },
  {
    "ID": 5,
    "Mass": 4.6231,
    "Name": "HFELXW",
    "Pos": [
      23363886070.0,
      -45936556074.0,
      0.0
    ],
    "Radius": 17
  },
  {
    "ID": 6,
    "Mass": 5.0327,
    "Name": "815ODS",
    "Pos": [
      -74302345491.0,
      -71358239564.0,
      0.0
    ],
    "Radius": 18
  },
  {
    "ID": 7,
    "Mass": 6.545,
    "Name": "4JAD7W",
    "Pos": [
      70112822579.0,
      25513603205.0,
      0.0
    ],
    "Radius": 15
  },
  {
    "ID": 8,
    "Mass": 6.2539,
    "Name": "QR0ZDK",
    "Pos": [
      -88110946977.0,
      -61306157996.0,
      0.0
    ],
    "Radius": 20
  },
  {
    "ID": 9,
    "Mass": 1.0403,
    "Name": "5WNP4R",
    "Pos": [
      -20956317387.0,
      -65764994431.0,
      0.0
    ],
    "Radius": 9
  },
  {
    "ID": 10,
    "Mass": 9.3349,
    "Name": "82U7PQ",
    "Pos": [
      42364930568.0,
      -90840373724.0,
      0.0
    ],
    "Radius": 17
  },
  {
    "ID": 11,
    "Mass": 4.877,
    "Name": "VBY2G2",
    "Pos": [
      50683029499.0,
      -66219250602.0,
      0.0
    ],
    "Radius": 12
  },
  {
    "ID": 12,
    "Mass": 8.4806,
    "Name": "2P4GSO",
    "Pos": [
      53069643989.0,
      -92349071778.0,
      0.0
    ],
    "Radius": 20
  },
  {
    "ID": 13,
    "Mass": 9.7905,
    "Name": "U5NQKE",
    "Pos": [
      -83159458842.0,
      15617437028.0,
      0.0
    ],
    "Radius": 11
  },
  {
    "ID": 14,
    "Mass": 9.7754,
    "Name": "1WZKDG",
    "Pos": [
      -65278111051.0,
      31990738388.0,
      0.0
    ],
    "Radius": 15
  },
  {
    "ID": 15,
    "Mass": 8.4321,
    "Name": "4AD27N",
    "Pos": [
      -25647932048.0,
      67538111997.0,
      0.0
    ],
    "Radius": 8
  },
  {
    "ID": 16,
    "Mass": 8.2973,
    "Name": "KUBOBT",
    "Pos": [
      -85908400265.0,
      -8959079505.0,
      0.0
    ],
    "Radius": 15
  },
  {
    "ID": 17,
    "Mass": 3.2383,
    "Name": "PZ9SSO",
    "Pos": [
      95238180293.0,
      -37721969031.0,
      0.0
    ],
    "Radius": 8
  },
  {
    "ID": 18,
    "Mass": 2.0891,
    "Name": "ZUTKHP",
    "Pos": [
      -25776176512.0,
      -66497607589.0,
      0.0
    ],
    "Radius": 20
  },
  {
    "ID": 19,
    "Mass": 4.9745,
    "Name": "F0ACFZ",
    "Pos": [
      38892065180.0,
      -86929172097.0,
      0.0
    ],
    "Radius": 18
  },
  {
    "ID": 20,
    "Mass": 3.3051,
    "Name": "7KUKAD",
    "Pos": [
      56098090857.0,
      -11113485249.0,
      0.0
    ],
    "Radius": 18
  },
  {
    "ID": 21,
    "Mass": 7.3375,
    "Name": "RJ5LA6",
    "Pos": [
      -60683844833.0,
      -5232415430.0,
      0.0
    ],
    "Radius": 6
  },
  {
    "ID": 22,
    "Mass": 8.902,
    "Name": "GA7OBV",
    "Pos": [
      -5598665210.0,
      -51860949829.0,
      0.0
    ],
    "Radius": 5
  },
  {
    "ID": 23,
    "Mass": 3.9066,
    "Name": "KB3FCA",
    "Pos": [
      29116068408.0,
      5159377882.0,
      0.0
    ],
    "Radius": 17
  },
  {
    "ID": 24,
    "Mass": 2.2382,
    "Name": "2MF1PW",
    "Pos": [
      23219360425.0,
      -73535056861.0,
      0.0
    ],
    "Radius": 23
  },
  {
    "ID": 25,
    "Mass": 2.7448,
    "Name": "OQO0MZ",
    "Pos": [
      9513998428.0,
      30115233019.0,
      0.0
    ],
    "Radius": 17
  },
  {
    "ID": 26,
    "Mass": 8.5616,
    "Name": "WLFAGI",
    "Pos": [
      -65849909977.0,
      95801132108.0,
      0.0
    ],
    "Radius": 23
  },
  {
    "ID": 27,
    "Mass": 9.2295,
    "Name": "5THBP6",
    "Pos": [
      62924524205.0,
      36481747839.0,
      0.0
    ],
    "Radius": 15
  },
  {
    "ID": 28,
    "Mass": 3.7142,
    "Name": "O4F2JZ",
    "Pos": [
      -24645657177.0,
      42093323228.0,
      0.0
    ],
    "Radius": 13
  },
  {
    "ID": 29,
    "Mass": 1.1733,
    "Name": "3JJ726",
    "Pos": [
      -61386281127.0,
      -98382914182.0,
      0.0
    ],
    "Radius": 8
  },
  {
    "ID": 30,
    "Mass": 3.0833,
    "Name": "ZGUFPJ",
    "Pos": [
      -92726075514.0,
      21398535709.0,
      0.0
    ],
    "Radius": 5
  },
  {
    "ID": 31,
    "Mass": 8.0753,
    "Name": "46I2EM",
    "Pos": [
      10672088479.0,
      18867853617.0,
      0.0
    ],
    "Radius": 20
  },
  {
    "ID": 32,
    "Mass": 2.4677,
    "Name": "FK6UOP",
    "Pos": [
      -31126808679.0,
      57177928337.0,
      0.0
    ],
    "Radius": 5
  },
  {
    "ID": 33,
    "Mass": 5.1586,
    "Name": "4D4HWD",
    "Pos": [
      18850403542.0,
      -33794416764.0,
      0.0
    ],
    "Radius": 13
  },
  {
    "ID": 34,
    "Mass": 8.4392,
    "Name": "7B6D5Q",
    "Pos": [
      93544277976.0,
      57497192240.0,
      0.0
    ],
    "Radius": 13
  },
  {
    "ID": 35,
    "Mass": 9.3811,
    "Name": "6B4LX9",
    "Pos": [
      7486636090.0,
      -6468257862.0,
      0.0
    ],
    "Radius": 15
  },
  {
    "ID": 36,
    "Mass": 6.4173,
    "Name": "PMORSD",
    "Pos": [
      -99155475321.0,
      -4068702015.0,
      0.0
    ],
    "Radius": 20
  },
  {
    "ID": 37,
    "Mass": 1.6105,
    "Name": "A5FMCF",
    "Pos": [
      2599808342.0,
      -91926090722.0,
      0.0
    ],
    "Radius": 8
  },
  {
    "ID": 38,
    "Mass": 1.0959,
    "Name": "WLJ0J6",
    "Pos": [
      31854930810.0,
      98229832416.0,
      0.0
    ],
    "Radius": 13
  },
  {
    "ID": 39,
    "Mass": 2.9718,
    "Name": "WHBF9V",
    "Pos": [
      -56667779702.0,
      -69819345707.0,
      0.0
    ],
    "Radius": 21
  },
  {
    "ID": 40,
    "Mass": 7.8522,
    "Name": "T07S2L",
    "Pos": [
      16005819630.0,
      -66084349763.0,
      0.0
    ],
    "Radius": 18
  },
  {
    "ID": 41,
    "Mass": 5.6529,
    "Name": "HFC86D",
    "Pos": [
      17706709537.0,
      48024840872.0,
      0.0
    ],
    "Radius": 16
  },
  {
    "ID": 42,
    "Mass": 5.2647,
    "Name": "Z1LXTR",
    "Pos": [
      65459739399.0,
      29829280968.0,
      0.0
    ],
    "Radius": 23
  },
  {
    "ID": 43,
    "Mass": 5.7953,
    "Name": "WVAVA5",
    "Pos": [
      -4266970010.0,
      -17335471481.0,
      0.0
    ],
    "Radius": 10
  },
  {
    "ID": 44,
    "Mass": 5.27,
    "Name": "KWMSFN",
    "Pos": [
      55865086091.0,
      98024435370.0,
      0.0
    ],
    "Radius": 15
  },
  {
    "ID": 45,
    "Mass": 7.5955,
    "Name": "OJCXYQ",
    "Pos": [
      84597294511.0,
      -47454183916.0,
      0.0
    ],
    "Radius": 12
  },
  {
    "ID": 46,
    "Mass": 8.7695,
    "Name": "WIKC3K",
    "Pos": [
      -24644585052.0,
      -77161008003.0,
      0.0
    ],
    "Radius": 20
  },
  {
    "ID": 47,
    "Mass": 3.8485,
    "Name": "57TD3A",
    "Pos": [
      58322492030.0,
      20145335626.0,
      0.0
    ],
    "Radius": 6
  },
  {
    "ID": 48,
    "Mass": 7.9684,
    "Name": "E9NWYY",
    "Pos": [
      51785463190.0,
      -72391551736.0,
      0.0
    ],
    "Radius": 14
  },
  {
    "ID": 49,
    "Mass": 4.3372,
    "Name": "YUQOK0",
    "Pos": [
      1728835460.0,
      42615258479.0,
      0.0
    ],
    "Radius": 15
  },
  {
    "ID": 50,
    "Mass": 2.3901,
    "Name": "9F6A6W",
    "Pos": [
      -46466052545.0,
      73783444549.0,
      0.0
    ],
    "Radius": 18
  },
  {
    "ID": 51,
    "Mass": 9.6792,
    "Name": "LDM89H",
    "Pos": [
      2155638313.0,
      -54033487538.0,
      0.0
    ],
    "Radius": 10
  },
  {
    "ID": 52,
    "Mass": 6.5638,
    "Name": "O6XQDS",
    "Pos": [
      18740236382.0,
      67310583192.0,
      0.0
    ],
    "Radius": 5
  },
  {
    "ID": 53,
    "Mass": 1.2684,
    "Name": "EHEZMS",
    "Pos": [
      34364200517.0,
      61039681929.0,
      0.0
    ],
    "Radius": 4
  },
  {
    "ID": 54,
    "Mass": 5.4822,
    "Name": "BK5NF9",
    "Pos": [
      62584001472.0,
      -44807421632.0,
      0.0
    ],
    "Radius": 11
  },
  {
    "ID": 55,
    "Mass": 6.6903,
    "Name": "6RNXAM",
    "Pos": [
      99040181417.0,
      -49541967443.0,
      0.0
    ],
    "Radius": 17
  },
  {
    "ID": 56,
    "Mass": 7.202,
    "Name": "QYIKY8",
    "Pos": [
      87148933910.0,
      -25072973546.0,
      0.0
    ],
    "Radius": 19
  },
  {
    "ID": 57,
    "Mass": 4.7299,
    "Name": "LRHPRL",
    "Pos": [
      -9181657187.0,
      -79747994725.0,
      0.0
    ],
    "Radius": 9
  },
  {
    "ID": 58,
    "Mass": 9.2613,
    "Name": "E7THBQ",
    "Pos": [
      -46084715064.0,
      10873871651.0,
      0.0
    ],
    "Radius": 20
  },
  {
    "ID": 59,
    "Mass": 8.9614,
    "Name": "T0F9N4",
    "Pos": [
      51455926480.0,
      -74597266804.0,
      0.0
    ],
    "Radius": 13
  },
  {
    "ID": 60,
    "Mass": 7.9913,
    "Name": "LWRIU4",
    "Pos": [
      -4687812629.0,
      -86892109942.0,
      0.0
    ],
    "Radius": 22
  },
  {
    "ID": 61,
    "Mass": 3.5256,
    "Name": "PMPVIH",
    "Pos": [
      -82815032845.0,
      -28913959129.0,
      0.0
    ],
    "Radius": 5
  },
  {
    "ID": 62,
    "Mass": 7.6392,
    "Name": "K15TEL",
    "Pos": [
      -38570758257.0,
      32479495080.0,
      0.0
    ],
    "Radius": 10
  },
  {
    "ID": 63,
    "Mass": 4.8886,
    "Name": "TAOE7A",
    "Pos": [
      65799328769.0,
      -6755539269.0,
      0.0
    ],
    "Radius": 15
  },
  {
    "ID": 64,
    "Mass": 7.2067,
    "Name": "Q5BRSY",
    "Pos": [
      -86042227133.0,
      -73128901608.0,
      0.0
    ],
    "Radius": 6
  },
  {
    "ID": 65,
    "Mass": 2.7093,
    "Name": "H3E0JZ",
    "Pos": [
      40078737441.0,
      70438776539.0,
      0.0
    ],
    "Radius": 6
  },
  {
    "ID": 66,
    "Mass": 7.4748,
    "Name": "3L6C5L",
    "Pos": [
      -32407237037.0,
      -32104455276.0,
      0.0
    ],
    "Radius": 16
  },
  {
    "ID": 67,
    "Mass": 3.5469,
    "Name": "TWP9TH",
    "Pos": [
      -49716827702.0,
      -49355580540.0,
      0.0
    ],
    "Radius": 16
  },
  {
    "ID": 68,
    "Mass": 4.6412,
    "Name": "G0VJP8",
    "Pos": [
      -84500342015.0,
      6617647980.0,
      0.0
    ],
    "Radius": 12
  },
  {
    "ID": 69,
    "Mass": 8.9356,
    "Name": "JQUGOK",
    "Pos": [
      -50186806224.0,
      -46005283946.0,
      0.0
    ],
    "Radius": 8
  },
  {
    "ID": 70,
    "Mass": 3.1975,
    "Name": "88H00P",
    "Pos": [
      10863174233.0,
      6678248763.0,
      0.0
    ],
    "Radius": 14
  },
  {
    "ID": 71,
    "Mass": 8.8412,
    "Name": "MR3AVY",
    "Pos": [
      43019890301.0,
      -13023757274.0,
      0.0
    ],
    "Radius": 18
  },
  {
    "ID": 72,
    "Mass": 1.8938,
    "Name": "T7479V",
    "Pos": [
      91805305833.0,
      51347296059.0,
      0.0
    ],
    "Radius": 21
  },
  {
    "ID": 73,
    "Mass": 3.6675,
    "Name": "AJ9HJ3",
    "Pos": [
      -69324513965.0,
      17219512367.0,
      0.0
    ],
    "Radius": 7
  },
  {
    "ID": 74,
    "Mass": 8.9522,
    "Name": "TSS3T5",
    "Pos": [
      11882975598.0,
      17077127000.0,
      0.0
    ],
    "Radius": 17
  },
  {
    "ID": 75,
    "Mass": 5.306,
    "Name": "WLSYMO",
    "Pos": [
      -52951717946.0,
      69959885310.0,
      0.0
    ],
    "Radius": 10
  },
  {
    "ID": 76,
    "Mass": 4.3924,
    "Name": "NG8LPD",
    "Pos": [
      -57255955559.0,
      -52510356493.0,
      0.0
    ],
    "Radius": 9
  },
  {
    "ID": 77,
    "Mass": 6.9548,
    "Name": "19H5MU",
    "Pos": [
      -87491559095.0,
      8739089526.0,
      0.0
    ],
    "Radius": 8
  },
  {
    "ID": 78,
    "Mass": 9.3912,
    "Name": "WH5N6H",
    "Pos": [
      49314216860.0,
      -44874301827.0,
      0.0
    ],
    "Radius": 16
  },
  {
    "ID": 79,
    "Mass": 4.5079,
    "Name": "FLWDKX",
    "Pos": [
      19837605505.0,
      -63153735859.0,
      0.0
    ],
    "Radius": 15
  },
  {
    "ID": 80,
    "Mass": 4.789,
    "Name": "YKIIF5",
    "Pos": [
      64943503513.0,
      8567625436.0,
      0.0
    ],
    "Radius": 8
  },
  {
    "ID": 81,
    "Mass": 2.0463,
    "Name": "7WE5Y8",
    "Pos": [
      64527970218.0,
      94003527437.0,
      0.0
    ],
    "Radius": 11
  },
  {
    "ID": 82,
    "Mass": 6.5529,
    "Name": "FBTFC1",
    "Pos": [
      -53347424114.0,
      -48815775312.0,
      0.0
    ],
    "Radius": 13
  },
  {
    "ID": 83,
    "Mass": 7.0204,
    "Name": "45W9WI",
    "Pos": [
      62654252916.0,
      -90611872946.0,
      0.0
    ],
    "Radius": 7
  },
  {
    "ID": 84,
    "Mass": 1.9871,
    "Name": "3NTZIT",
    "Pos": [
      99140615792.0,
      -69835028379.0,
      0.0
    ],
    "Radius": 8
  },
  {
    "ID": 85,
    "Mass": 8.6773,
    "Name": "5PF3L6",
    "Pos": [
      93224996875.0,
      76607699967.0,
      0.0
    ],
    "Radius": 18
  },
  {
    "ID": 86,
    "Mass": 8.3717,
    "Name": "UQUW6J",
    "Pos": [
      -99536760876.0,
      23940145691.0,
      0.0
    ],
    "Radius": 10
  },
  {
    "ID": 87,
    "Mass": 5.809,
    "Name": "A178MN",
    "Pos": [
      81521877257.0,
      24697532557.0,
      0.0
    ],
    "Radius": 21
  },
  {
    "ID": 88,
    "Mass": 3.3647,
    "Name": "BSMCEJ",
    "Pos": [
      -19875004910.0,
      55945179714.0,
      0.0
    ],
    "Radius": 16
  },
  {
    "ID": 89,
    "Mass": 9.1017,
    "Name": "Q4K5LI",
    "Pos": [
      79015500756.0,
      -12459336285.0,
      0.0
    ],
    "Radius": 13
  },
  {
    "ID": 90,
    "Mass": 7.8743,
    "Name": "HXIUZ5",
    "Pos": [
      -5492122818.0,
      -43794346072.0,
      0.0
    ],
    "Radius": 11
  },
  {
    "ID": 91,
    "Mass": 9.6398,
    "Name": "90L0OE",
    "Pos": [
      -1768558267.0,
      -30526392657.0,
      0.0
    ],
    "Radius": 18
  },
  {
    "ID": 92,
    "Mass": 5.9651,
    "Name": "0N9K2Q",
    "Pos": [
      54294278506.0,
      63705839845.0,
      0.0
    ],
    "Radius": 14
  },
  {
    "ID": 93,
    "Mass": 1.4594,
    "Name": "BFOCNL",
    "Pos": [
      -72876778397.0,
      70259147288.0,
      0.0
    ],
    "Radius": 6
  },
  {
    "ID": 94,
    "Mass": 4.6109,
    "Name": "IJ79JY",
    "Pos": [
      -87343481401.0,
      -46955305764.0,
      0.0
    ],
    "Radius": 16
  },
  {
    "ID": 95,
    "Mass": 8.2024,
    "Name": "HEY6KV",
    "Pos": [
      20314993436.0,
      -26615106024.0,
      0.0
    ],
    "Radius": 7
  },
  {
    "ID": 96,
    "Mass": 5.0465,
    "Name": "5XVQ21",
    "Pos": [
      -60191352881.0,
      99057617926.0,
      0.0
    ],
    "Radius": 10
  },
  {
    "ID": 97,
    "Mass": 2.7591,
    "Name": "NWQ5YL",
    "Pos": [
      29700924450.0,
      148427748.0,
      0.0
    ],
    "Radius": 10
  },
  {
    "ID": 98,
    "Mass": 1.7275,
    "Name": "9IYG6V",
    "Pos": [
      63851082671.0,
      -94661793209.0,
      0.0
    ],
    "Radius": 4
  },
  {
    "ID": 99,
    "Mass": 6.5924,
    "Name": "95ZN5L",
    "Pos": [
      19113990750.0,
      83159551760.0,
      0.0
    ],
    "Radius": 17
  },
  {
    "ID": 100,
    "Mass": 8.37,
    "Name": "63WLSH",
    "Pos": [
      -52996527342.0,
      -67995621861.0,
      0.0
    ],
    "Radius": 4
  },
  {
    "ID": 101,
    "Mass": 8.724,
    "Name": "YFOB8G",
    "Pos": [
      -30717796664.0,
      9452458056.0,
      0.0
    ],
    "Radius": 8
  },
  {
    "ID": 102,
    "Mass": 1.3751,
    "Name": "V6K5GF",
    "Pos": [
      86213033350.0,
      -3346314328.0,
      0.0
    ],
    "Radius": 6
  },
  {
    "ID": 103,
    "Mass": 7.4559,
    "Name": "79YGJ2",
    "Pos": [
      -94610889289.0,
      -75583705069.0,
      0.0
    ],
    "Radius": 5
  },
  {
    "ID": 104,
    "Mass": 9.6416,
    "Name": "31KZTV",
    "Pos": [
      22648909313.0,
      -72536242344.0,
      0.0
    ],
    "Radius": 9
  },
  {
    "ID": 105,
    "Mass": 5.1102,
    "Name": "BFQ4QT",
    "Pos": [
      -52639851754.0,
      -86943487275.0,
      0.0
    ],
    "Radius": 7
  },
  {
    "ID": 106,
    "Mass": 2.6284,
    "Name": "ISRFZU",
    "Pos": [
      24562866045.0,
      -73520301702.0,
      0.0
    ],
    "Radius": 9
  },
  {
    "ID": 107,
    "Mass": 2.0367,
    "Name": "N0Y8DF",
    "Pos": [
      -43361276959.0,
      -38685368097.0,
      0.0
    ],
    "Radius": 19
  },
  {
    "ID": 108,
    "Mass": 1.905,
    "Name": "7F6ISO",
    "Pos": [
      96368444215.0,
      30127973098.0,
      0.0
    ],
    "Radius": 11
  },
  {
    "ID": 109,
    "Mass": 9.3443,
    "Name": "77ZZF5",
    "Pos": [
      76831731458.0,
      -22264071208.0,
      0.0
    ],
    "Radius": 11
  },
  {
    "ID": 110,
    "Mass": 3.6069,
    "Name": "NERZDR",
    "Pos": [
      92559745830.0,
      -65836493399.0,
      0.0
    ],
    "Radius": 6
  },
  {
    "ID": 111,
    "Mass": 6.1012,
    "Name": "0KFHZ2",
    "Pos": [
      79461229676.0,
      38313217299.0,
      0.0
    ],
    "Radius": 6
  },
  {
    "ID": 112,
    "Mass": 6.5372,
    "Name": "WOCWOZ",
    "Pos": [
      93766299108.0,
      73120200292.0,
      0.0
    ],
    "Radius": 13
  },
  {
    "ID": 113,
    "Mass": 9.2565,
    "Name": "4ILE7S",
    "Pos": [
      43213773829.0,
      34525794560.0,
      0.0
    ],
    "Radius": 21
  },
  {
    "ID": 114,
    "Mass": 2.279,
    "Name": "O36DXR",
    "Pos": [
      -97112401238.0,
      -90063339930.0,
      0.0
    ],
    "Radius": 7
  },
  {
    "ID": 115,
    "Mass": 9.1207,
    "Name": "BJEE91",
    "Pos": [
      -16378599219.0,
      -73806433783.0,
      0.0
    ],
    "Radius": 12
  },
  {
    "ID": 116,
    "Mass": 7.0642,
    "Name": "4G5DSV",
    "Pos": [
      27400629388.0,
      44654829121.0,
      0.0
    ],
    "Radius": 5
  },
  {
    "ID": 117,
    "Mass": 1.5905,
    "Name": "8JWCGT",
    "Pos": [
      -93765597365.0,
      70610367336.0,
      0.0
    ],
    "Radius": 8
  },
  {
    "ID": 118,
    "Mass": 1.9125,
    "Name": "UEJO5K",
    "Pos": [
      81065198396.0,
      77202341358.0,
      0.0
    ],
    "Radius": 7
  },
  {
    "ID": 119,
    "Mass": 5.6924,
    "Name": "C4DFOC",
    "Pos": [
      -94389171507.0,
      46418056161.0,
      0.0
    ],
    "Radius": 10
  },
  {
    "ID": 120,
    "Mass": 5.8051,
    "Name": "NFQON3",
    "Pos": [
      -10703272201.0,
      -91256573902.0,
      0.0
    ],
    "Radius": 5
  },
  {
    "ID": 121,
    "Mass": 3.4029,
    "Name": "Z9ZG60",
    "Pos": [
      73285988314.0,
      27353191252.0,
      0.0
    ],
    "Radius": 8
  },
  {
    "ID": 122,
    "Mass": 8.0477,
    "Name": "V4WBG6",
    "Pos": [
      -13839183400.0,
      37271237550.0,
      0.0
    ],
    "Radius": 7
  },
  {
    "ID": 123,
    "Mass": 1.3047,
    "Name": "BZ5TKS",
    "Pos": [
      -29597801001.0,
      88861994654.0,
      0.0
    ],
    "Radius": 23
  },
  {
    "ID": 124,
    "Mass": 7.5663,
    "Name": "ID62ZY",
    "Pos": [
      74037740523.0,
      -24651957472.0,
      0.0
    ],
    "Radius": 8
  },
  {
    "ID": 125,
    "Mass": 2.8179,
    "Name": "DZK028",
    "Pos": [
      9071746142.0,
      54262751910.0,
      0.0
    ],
    "Radius": 6
  },
  {
    "ID": 126,
    "Mass": 9.898,
    "Name": "3IKASC",
    "Pos": [
      -33193129109.0,
      92337843057.0,
      0.0
    ],
    "Radius": 10
  },
  {
    "ID": 127,
    "Mass": 7.2643,
    "Name": "Z7QWTT",
    "Pos": [
      34305749675.0,
      88082540591.0,
      0.0
    ],
    "Radius": 18
  },
  {
    "ID": 128,
    "Mass": 2.1593,
    "Name": "7JI2YV",
    "Pos": [
      -24047137464.0,
      -2407886631.0,
      0.0
    ],
    "Radius": 13
  },
  {
    "ID": 129,
    "Mass": 5.7915,
    "Name": "B96C54",
    "Pos": [
      -47405864586.0,
      -16734905891.0,
      0.0
    ],
    "Radius": 6
  },
  {
    "ID": 130,
    "Mass": 6.8923,
    "Name": "SDCQVW",
    "Pos": [
      -15674151186.0,
      4090063351.0,
      0.0
    ],
    "Radius": 17
  },
  {
    "ID": 131,
    "Mass": 3.2127,
    "Name": "6RBF9N",
    "Pos": [
      -83406595126.0,
      93065605565.0,
      0.0
    ],
    "Radius": 23
  },
  {
    "ID": 132,
    "Mass": 6.3621,
    "Name": "U8UYV0",
    "Pos": [
      -76095230416.0,
      -14856518808.0,
      0.0
    ],
    "Radius": 21
  },
  {
    "ID": 133,
    "Mass": 4.9871,
    "Name": "D0H5TD",
    "Pos": [
      -97445356209.0,
      53753272311.0,
      0.0
    ],
    "Radius": 14
  },
  {
    "ID": 134,
    "Mass": 2.1193,
    "Name": "SB5YB3",
    "Pos": [
      -24185780802.0,
      -26292495237.0,
      0.0
    ],
    "Radius": 18
  },
  {
    "ID": 135,
    "Mass": 5.6701,
    "Name": "PGOXZJ",
    "Pos": [
      -21656378878.0,
      61597194802.0,
      0.0
    ],
    "Radius": 9
  },
  {
    "ID": 136,
    "Mass": 6.0592,
    "Name": "BOVZM1",
    "Pos": [
      83188613350.0,
      19041616628.0,
      0.0
    ],
    "Radius": 18
  },
  {
    "ID": 137,
    "Mass": 3.9987,
    "Name": "6Y6O8Q",
    "Pos": [
      -92155479692.0,
      -42574035756.0,
      0.0
    ],
    "Radius": 8
  },
  {
    "ID": 138,
    "Mass": 4.246,
    "Name": "6377MP",
    "Pos": [
      76765263138.0,
      -75855851512.0,
      0.0
    ],
    "Radius": 8
  },
  {
    "ID": 139,
    "Mass": 9.5056,
    "Name": "LBI92L",
    "Pos": [
      -54751937877.0,
      -33965084349.0,
      0.0
    ],
    "Radius": 12
  },
  {
    "ID": 140,
    "Mass": 1.1727,
    "Name": "9R7OXQ",
    "Pos": [
      -58059702294.0,
      5164982427.0,
      0.0
    ],
    "Radius": 20
  },
  {
    "ID": 141,
    "Mass": 4.7467,
    "Name": "435RMQ",
    "Pos": [
      46814125942.0,
      -96628098223.0,
      0.0
    ],
    "Radius": 7
  },
  {
    "ID": 142,
    "Mass": 5.8179,
    "Name": "KM65YZ",
    "Pos": [
      53074763969.0,
      -1329903664.0,
      0.0
    ],
    "Radius": 18
  },
  {
    "ID": 143,
    "Mass": 4.3826,
    "Name": "2INHU3",
    "Pos": [
      -74838343855.0,
      86335660843.0,
      0.0
    ],
    "Radius": 22
  },
  {
    "ID": 144,
    "Mass": 8.6602,
    "Name": "KAEG9S",
    "Pos": [
      -35203329876.0,
      -41764465048.0,
      0.0
    ],
    "Radius": 11
  },
  {
    "ID": 145,
    "Mass": 8.8224,
    "Name": "O6RF4S",
    "Pos": [
      97802138046.0,
      -59522657723.0,
      0.0
    ],
    "Radius": 11
  },
  {
    "ID": 146,
    "Mass": 3.1426,
    "Name": "QEL22V",
    "Pos": [
      634558775.0,
      28990524581.0,
      0.0
    ],
    "Radius": 19
  },
  {
    "ID": 147,
    "Mass": 4.1676,
    "Name": "6PK7D3",
    "Pos": [
      -45335198919.0,
      -39610499831.0,
      0.0
    ],
    "Radius": 4
  },
  {
    "ID": 148,
    "Mass": 7.2984,
    "Name": "P7FQRU",
    "Pos": [
      -25594975741.0,
      55674781664.0,
      0.0
    ],
    "Radius": 17
  },
  {
    "ID": 149,
    "Mass": 9.9841,
    "Name": "V44SKA",
    "Pos": [
      62958329675.0,
      28096524416.0,
      0.0
    ],
    "Radius": 7
  },
  {
    "ID": 150,
    "Mass": 2.2228,
    "Name": "IVZ0R7",
    "Pos": [
      28747853407.0,
      71958395096.0,
      0.0
    ],
    "Radius": 7
  },
  {
    "ID": 151,
    "Mass": 5.797,
    "Name": "SN2ITD",
    "Pos": [
      88643167591.0,
      84462543490.0,
      0.0
    ],
    "Radius": 10
  },
  {
    "ID": 152,
    "Mass": 9.1898,
    "Name": "27CSL4",
    "Pos": [
      -94242095083.0,
      34533369415.0,
      0.0
    ],
    "Radius": 10
  },
  {
    "ID": 153,
    "Mass": 8.9948,
    "Name": "VIW9HX",
    "Pos": [
      -5807053478.0,
      -94709292345.0,
      0.0
    ],
    "Radius": 20
  },
  {
    "ID": 154,
    "Mass": 6.8207,
    "Name": "T69TA3",
    "Pos": [
      89978669776.0,
      43513638148.0,
      0.0
    ],
    "Radius": 13
  },
  {
    "ID": 155,
    "Mass": 3.1964,
    "Name": "QTHSJB",
    "Pos": [
      86044681929.0,
      -8615447750.0,
      0.0
    ],
    "Radius": 14
  },
  {
    "ID": 156,
    "Mass": 2.9247,
    "Name": "XC3IDX",
    "Pos": [
      57239163579.0,
      -51107436780.0,
      0.0
    ],
    "Radius": 6
  },
  {
    "ID": 157,
    "Mass": 9.975,
    "Name": "DUJJES",
    "Pos": [
      5500912380.0,
      -68165599266.0,
      0.0
    ],
    "Radius": 8
  },
  {
    "ID": 158,
    "Mass": 1.5593,
    "Name": "LGS45J",
    "Pos": [
      64287410875.0,
      -16959246450.0,
      0.0
    ],
    "Radius": 12
  },
  {
    "ID": 159,
    "Mass": 5.8689,
    "Name": "PSK36I",
    "Pos": [
      -37279123281.0,
      -56220980948.0,
      0.0
    ],
    "Radius": 20
  },
  {
    "ID": 160,
    "Mass": 3.0875,
    "Name": "Y0WAYS",
    "Pos": [
      90397814908.0,
      61201719619.0,
      0.0
    ],
    "Radius": 22
  },
  {
    "ID": 161,
    "Mass": 5.5957,
    "Name": "QICKMG",
    "Pos": [
      -20545738093.0,
      36267546572.0,
      0.0
    ],
    "Radius": 13
  },
  {
    "ID": 162,
    "Mass": 7.4761,
    "Name": "C0V3YB",
    "Pos": [
      69831203912.0,
      -20408616125.0,
      0.0
    ],
    "Radius": 15
  },
  {
    "ID": 163,
    "Mass": 5.371,
    "Name": "81DZSJ",
    "Pos": [
      28222261947.0,
      -79272586123.0,
      0.0
    ],
    "Radius": 13
  },
  {
    "ID": 164,
    "Mass": 3.4325,
    "Name": "NA8WV8",
    "Pos": [
      93732588662.0,
      1244977901.0,
      0.0
    ],
    "Radius": 6
  },
  {
    "ID": 165,
    "Mass": 5.2968,
    "Name": "Y2JLCW",
    "Pos": [
      -10644607221.0,
      -14883938500.0,
      0.0
    ],
    "Radius": 19
  },
  {
    "ID": 166,
    "Mass": 3.9105,
    "Name": "ZR1XVA",
    "Pos": [
      -43183650479.0,
      27786977251.0,
      0.0
    ],
    "Radius": 22
  },
  {
    "ID": 167,
    "Mass": 3.9293,
    "Name": "B7A3NI",
    "Pos": [
      36958401490.0,
      844072638.0,
      0.0
    ],
    "Radius": 10
  },
  {
    "ID": 168,
    "Mass": 3.8771,
    "Name": "DKD2RR",
    "Pos": [
      68584117084.0,
      33437895142.0,
      0.0
    ],
    "Radius": 23
  },
  {
    "ID": 169,
    "Mass": 7.2641,
    "Name": "CCBFUE",
    "Pos": [
      98096308743.0,
      -10475948796.0,
      0.0
    ],
    "Radius": 9
  },
  {
    "ID": 170,
    "Mass": 2.176,
    "Name": "9WE6HN",
    "Pos": [
      -40430725328.0,
      -61905836535.0,
      0.0
    ],
    "Radius": 10
  },
  {
    "ID": 171,
    "Mass": 1.3827,
    "Name": "47XF8U",
    "Pos": [
      -96491073278.0,
      28380642450.0,
      0.0
    ],
    "Radius": 8
  },
  {
    "ID": 172,
    "Mass": 9.2847,
    "Name": "TBP3X6",
    "Pos": [
      6557327352.0,
      50131114060.0,
      0.0
    ],
    "Radius": 19
  },
  {
    "ID": 173,
    "Mass": 3.6895,
    "Name": "JBUZSW",
    "Pos": [
      -34525348856.0,
      29318006472.0,
      0.0
    ],
    "Radius": 18
  },
  {
    "ID": 174,
    "Mass": 7.46,
    "Name": "U1IO9H",
    "Pos": [
      -73637252535.0,
      -24046639715.0,
      0.0
    ],
    "Radius": 21
  },
  {
    "ID": 175,
    "Mass": 6.9781,
    "Name": "2QME82",
    "Pos": [
      -75177185931.0,
      -64863625469.0,
      0.0
    ],
    "Radius": 19
  },
  {
    "ID": 176,
    "Mass": 2.3391,
    "Name": "SE02P7",
    "Pos": [
      10976590861.0,
      -90830182096.0,
      0.0
    ],
    "Radius": 20
  },
  {
    "ID": 177,
    "Mass": 9.9059,
    "Name": "SS2L8W",
    "Pos": [
      -24748757911.0,
      57658412368.0,
      0.0
    ],
    "Radius": 22
  },
  {
    "ID": 178,
    "Mass": 8.4773,
    "Name": "Z9N64M",
    "Pos": [
      -18695216395.0,
      -30114570610.0,
      0.0
    ],
    "Radius": 9
  },
  {
    "ID": 179,
    "Mass": 2.2279,
    "Name": "6VQ8EF",
    "Pos": [
      80642386196.0,
      15495295233.0,
      0.0
    ],
    "Radius": 8
  },
  {
    "ID": 180,
    "Mass": 5.8995,
    "Name": "XHKOCP",
    "Pos": [
      -9529418123.0,
      57979716864.0,
      0.0
    ],
    "Radius": 5
  },
  {
    "ID": 181,
    "Mass": 5.203,
    "Name": "0C0OPK",
    "Pos": [
      -66001838408.0,
      90417362343.0,
      0.0
    ],
    "Radius": 14
  },
  {
    "ID": 182,
    "Mass": 4.0052,
    "Name": "H0XCCY",
    "Pos": [
      18230048403.0,
      42527147759.0,
      0.0
    ],
    "Radius": 9
  },
  {
    "ID": 183,
    "Mass": 7.0549,
    "Name": "K351P4",
    "Pos": [
      83319817659.0,
      76554434989.0,
      0.0
    ],
    "Radius": 4
  },
  {
    "ID": 184,
    "Mass": 1.0744,
    "Name": "4ENE4B",
    "Pos": [
      -54486711828.0,
      -27902618066.0,
      0.0
    ],
    "Radius": 10
  },
  {
    "ID": 185,
    "Mass": 8.3533,
    "Name": "VS6L2E",
    "Pos": [
      87281943491.0,
      65933832963.0,
      0.0
    ],
    "Radius": 21
  },
  {
    "ID": 186,
    "Mass": 3.4421,
    "Name": "OF71RE",
    "Pos": [
      -43251023490.0,
      -44165731059.0,
      0.0
    ],
    "Radius": 15
  },
  {
    "ID": 187,
    "Mass": 6.6281,
    "Name": "9CL2XM",
    "Pos": [
      46361527026.0,
      -54185653042.0,
      0.0
    ],
    "Radius": 9
  },
  {
    "ID": 188,
    "Mass": 3.4038,
    "Name": "1IKVLK",
    "Pos": [
      84497682418.0,
      -86817025525.0,
      0.0
    ],
    "Radius": 14
  },
  {
    "ID": 189,
    "Mass": 3.4967,
    "Name": "E3FTEI",
    "Pos": [
      -60582828800.0,
      -86113648114.0,
      0.0
    ],
    "Radius": 9
  },
  {
    "ID": 190,
    "Mass": 4.3113,
    "Name": "V88OOO",
    "Pos": [
      -39834598196.0,
      -55416091805.0,
      0.0
    ],
    "Radius": 19
  },
  {
    "ID": 191,
    "Mass": 1.3833,
    "Name": "Y78OB1",
    "Pos": [
      59995388548.0,
      93862550397.0,
      0.0
    ],
    "Radius": 5
  },
  {
    "ID": 192,
    "Mass": 9.7359,
    "Name": "SLXKUY",
    "Pos": [
      -67803357810.0,
      8669621514.0,
      0.0
    ],
    "Radius": 20
  },
  {
    "ID": 193,
    "Mass": 5.6869,
    "Name": "CM4ZDG",
    "Pos": [
      -34677506077.0,
      -98321725804.0,
      0.0
    ],
    "Radius": 4
  },
  {
    "ID": 194,
    "Mass": 6.9985,
    "Name": "D85R7R",
    "Pos": [
      85865959233.0,
      -58703940344.0,
      0.0
    ],
    "Radius": 11
  },
  {
    "ID": 195,
    "Mass": 8.6164,
    "Name": "YUZBR2",
    "Pos": [
      -66350133626.0,
      49770991947.0,
      0.0
    ],
    "Radius": 13
  },
  {
    "ID": 196,
    "Mass": 4.9603,
    "Name": "7KLS2J",
    "Pos": [
      57977709229.0,
      -69592939229.0,
      0.0
    ],
    "Radius": 8
  },
  {
    "ID": 197,
    "Mass": 3.0505,
    "Name": "BIHZHT",
    "Pos": [
      64519888358.0,
      -23011360950.0,
      0.0
    ],
    "Radius": 7
  },
  {
    "ID": 198,
    "Mass": 5.4458,
    "Name": "0XZWAI",
    "Pos": [
      12496781811.0,
      21387367820.0,
      0.0
    ],
    "Radius": 8
  },
  {
    "ID": 199,
    "Mass": 2.6069,
    "Name": "DR04IM",
    "Pos": [
      12787523707.0,
      -92456724273.0,
      0.0
    ],
    "Radius": 14
  },
  {
    "ID": 200,
    "Mass": 9.8319,
    "Name": "DA3WP7",
    "Pos": [
      52121033400.0,
      -22476889558.0,
      0.0
    ],
    "Radius": 5
  },
  {
    "ID": 201,
    "Mass": 7.1485,
    "Name": "H9SOV0",
    "Pos": [
      7283586021.0,
      -38363303206.0,
      0.0
    ],
    "Radius": 21
  },
  {
    "ID": 202,
    "Mass": 6.5166,
    "Name": "NVRO6E",
    "Pos": [
      28370170228.0,
      61406827535.0,
      0.0
    ],
    "Radius": 10
  },
  {
    "ID": 203,
    "Mass": 9.8793,
    "Name": "UDFBFA",
    "Pos": [
      -6879087734.0,
      93632007498.0,
      0.0
    ],
    "Radius": 20
  },
  {
    "ID": 204,
    "Mass": 4.7293,
    "Name": "N9ZPFW",
    "Pos": [
      -75752523734.0,
      -21274377731.0,
      0.0
    ],
    "Radius": 17
  },
  {
    "ID": 205,
    "Mass": 9.9467,
    "Name": "ZVKVCQ",
    "Pos": [
      -15328610394.0,
      20963468290.0,
      0.0
    ],
    "Radius": 16
  },
  {
    "ID": 206,
    "Mass": 7.9014,
    "Name": "IAE8YG",
    "Pos": [
      28332397464.0,
      -61238143657.0,
      0.0
    ],
    "Radius": 17
  },
  {
    "ID": 207,
    "Mass": 8.0454,
    "Name": "9E6KIG",
    "Pos": [
      -88934132693.0,
      87881604186.0,
      0.0
    ],
    "Radius": 5
  },
  {
    "ID": 208,
    "Mass": 2.1678,
    "Name": "2K639D",
    "Pos": [
      22979693669.0,
      -92920086292.0,
      0.0
    ],
    "Radius": 14
  },
  {
    "ID": 209,
    "Mass": 8.7381,
    "Name": "2HG8HA",
    "Pos": [
      75173551824.0,
      18740793765.0,
      0.0
    ],
    "Radius": 22
  },
  {
    "ID": 210,
    "Mass": 4.1767,
    "Name": "QZ9MVA",
    "Pos": [
      10072271262.0,
      1296647199.0,
      0.0
    ],
    "Radius": 14
  },
  {
    "ID": 211,
    "Mass": 3.765,
    "Name": "4PGFP3",
    "Pos": [
      -87908553953.0,
      42495929252.0,
      0.0
    ],
    "Radius": 6
  },
  {
    "ID": 212,
    "Mass": 8.286,
    "Name": "L7FOF8",
    "Pos": [
      -66032901859.0,
      5466364354.0,
      0.0
    ],
    "Radius": 16
  },
  {
    "ID": 213,
    "Mass": 9.4199,
    "Name": "GOETNC",
    "Pos": [
      -55100981292.0,
      -75807869145.0,
      0.0
    ],
    "Radius": 5
  },
  {
    "ID": 214,
    "Mass": 5.0635,
    "Name": "VFFMSF",
    "Pos": [
      10213819529.0,
      -1108739784.0,
      0.0
    ],
    "Radius": 20
  },
  {
    "ID": 215,
    "Mass": 2.5771,
    "Name": "XLG8TO",
    "Pos": [
      41203337425.0,
      -97720982880.0,
      0.0
    ],
    "Radius": 13
  },
  {
    "ID": 216,
    "Mass": 1.6229,
    "Name": "F0KY50",
    "Pos": [
      -69641336267.0,
      -60274254024.0,
      0.0
    ],
    "Radius": 15
  },
  {
    "ID": 217,
    "Mass": 9.4922,
    "Name": "C1X9CL",
    "Pos": [
      78189328446.0,
      50474080362.0,
      0.0
    ],
    "Radius": 22
  },
  {
    "ID": 218,
    "Mass": 7.4758,
    "Name": "ZXG5TP",
    "Pos": [
      -28484846709.0,
      -59375927953.0,
      0.0
    ],
    "Radius": 7
  },
  {
    "ID": 219,
    "Mass": 7.9083,
    "Name": "JHV0QL",
    "Pos": [
      87414614182.0,
      56728423837.0,
      0.0
    ],
    "Radius": 23
  },
  {
    "ID": 220,
    "Mass": 3.729,
    "Name": "BPLT0L",
    "Pos": [
      -70292718026.0,
      77579247982.0,
      0.0
    ],
    "Radius": 8
  },
  {
    "ID": 221,
    "Mass": 3.5272,
    "Name": "60FWO9",
    "Pos": [
      42207411909.0,
      -18155921157.0,
      0.0
    ],
    "Radius": 12
  },
  {
    "ID": 222,
    "Mass": 5.0992,
    "Name": "9HRW5V",
    "Pos": [
      43354291256.0,
      -53290004604.0,
      0.0
    ],
    "Radius": 22
  },
  {
    "ID": 223,
    "Mass": 9.6975,
    "Name": "0ONCZE",
    "Pos": [
      -76253036157.0,
      41259173461.0,
      0.0
    ],
    "Radius": 13
  },
  {
    "ID": 224,
    "Mass": 6.8546,
    "Name": "J1T3GQ",
    "Pos": [
      -56506984563.0,
      12424808693.0,
      0.0
    ],
    "Radius": 10
  },
  {
    "ID": 225,
    "Mass": 4.2415,
    "Name": "BC80ZZ",
    "Pos": [
      -56316633812.0,
      38323001368.0,
      0.0
    ],
    "Radius": 7
  },
  {
    "ID": 226,
    "Mass": 1.3677,
    "Name": "THWX06",
    "Pos": [
      46012841561.0,
      84907023854.0,
      0.0
    ],
    "Radius": 7
  },
  {
    "ID": 227,
    "Mass": 6.488,
    "Name": "VUSECF",
    "Pos": [
      25342842497.0,
      -4843813617.0,
      0.0
    ],
    "Radius": 18
  },
  {
    "ID": 228,
    "Mass": 9.3144,
    "Name": "PB6C16",
    "Pos": [
      -17010287072.0,
      -42492961397.0,
      0.0
    ],
    "Radius": 20
  },
  {
    "ID": 229,
    "Mass": 3.3936,
    "Name": "HDZNX5",
    "Pos": [
      32897244337.0,
      -91636084340.0,
      0.0
    ],
    "Radius": 13
  },
  {
    "ID": 230,
    "Mass": 6.1651,
    "Name": "OLXOAE",
    "Pos": [
      25128959067.0,
      59074655093.0,
      0.0
    ],
    "Radius": 22
  },
  {
    "ID": 231,
    "Mass": 1.3153,
    "Name": "5AI58E",
    "Pos": [
      -95104153627.0,
      49339582388.0,
      0.0
    ],
    "Radius": 21
  },
  {
    "ID": 232,
    "Mass": 6.7429,
    "Name": "0IS1N3",
    "Pos": [
      -66730475862.0,
      -40928976090.0,
      0.0
    ],
    "Radius": 21
  },
  {
    "ID": 233,
    "Mass": 3.8543,
    "Name": "Q6XHIM",
    "Pos": [
      67303094657.0,
      -2125259681.0,
      0.0
    ],
    "Radius": 12
  },
  {
    "ID": 234,
    "Mass": 8.9413,
    "Name": "7OCWMS",
    "Pos": [
      -53242304373.0,
      7241709374.0,
      0.0
    ],
    "Radius": 17
  },
  {
    "ID": 235,
    "Mass": 3.1865,
    "Name": "W3ERRA",
    "Pos": [
      37472826112.0,
      -23634869025.0,
      0.0
    ],
    "Radius": 19
  },
  {
    "ID": 236,
    "Mass": 6.2688,
    "Name": "4NRGMM",
    "Pos": [
      -754258830.0,
      26643738573.0,
      0.0
    ],
    "Radius": 12
  },
  {
    "ID": 237,
    "Mass": 7.8995,
    "Name": "NF17AD",
    "Pos": [
      54002098259.0,
      21825417072.0,
      0.0
    ],
    "Radius": 13
  },
  {
    "ID": 238,
    "Mass": 1.2819,
    "Name": "H3J5SS",
    "Pos": [
      -49450197491.0,
      5823097845.0,
      0.0
    ],
    "Radius": 19
  },
  {
    "ID": 239,
    "Mass": 5.8532,
    "Name": "119DMA",
    "Pos": [
      97076044116.0,
      78700131834.0,
      0.0
    ],
    "Radius": 8
  },
  {
    "ID": 240,
    "Mass": 3.6441,
    "Name": "5I1SV4",
    "Pos": [
      -69234727462.0,
      -12010792604.0,
      0.0
    ],
    "Radius": 23
  },
  {
    "ID": 241,
    "Mass": 3.6474,
    "Name": "T7EP4A",
    "Pos": [
      60159321220.0,
      93349918306.0,
      0.0
    ],
    "Radius": 7
  },
  {
    "ID": 242,
    "Mass": 4.0835,
    "Name": "SLJJYP",
    "Pos": [
      23993881365.0,
      51954331539.0,
      0.0
    ],
    "Radius": 10
  },
  {
    "ID": 243,
    "Mass": 8.4774,
    "Name": "8CCH3T",
    "Pos": [
      10459361698.0,
      67596878052.0,
      0.0
    ],
    "Radius": 18
  },
  {
    "ID": 244,
    "Mass": 1.5505,
    "Name": "G1MKX3",
    "Pos": [
      28829504092.0,
      44805536798.0,
      0.0
    ],
    "Radius": 12
  },
  {
    "ID": 245,
    "Mass": 3.8542,
    "Name": "4QXGL0",
    "Pos": [
      94970667643.0,
      -39809154575.0,
      0.0
    ],
    "Radius": 12
  },
  {
    "ID": 246,
    "Mass": 7.7837,
    "Name": "ZMEO5T",
    "Pos": [
      24020477095.0,
      -35175604861.0,
      0.0
    ],
    "Radius": 15
  },
  {
    "ID": 247,
    "Mass": 3.7192,
    "Name": "H51F5N",
    "Pos": [
      31610356569.0,
      -1271165502.0,
      0.0
    ],
    "Radius": 22
  },
  {
    "ID": 248,
    "Mass": 2.3075,
    "Name": "YV153G",
    "Pos": [
      -58089038662.0,
      -63741386934.0,
      0.0
    ],
    "Radius": 17
  },
  {
    "ID": 249,
    "Mass": 6.417,
    "Name": "DZ45OJ",
    "Pos": [
      -28952749912.0,
      -45053873944.0,
      0.0
    ],
    "Radius": 13
  },
  {
    "ID": 250,
    "Mass": 1.3997,
    "Name": "DHVJ72",
    "Pos": [
      -84288105042.0,
      -97035713953.0,
      0.0
    ],
    "Radius": 12
  },
  {
    "ID": 251,
    "Mass": 7.2819,
    "Name": "0PI8XP",
    "Pos": [
      -39151541097.0,
      9005235747.0,
      0.0
    ],
    "Radius": 14
  },
  {
    "ID": 252,
    "Mass": 8.0577,
    "Name": "KY0CHL",
    "Pos": [
      -93855984645.0,
      -73866910146.0,
      0.0
    ],
    "Radius": 18
  },
  {
    "ID": 253,
    "Mass": 7.8247,
    "Name": "U7S54X",
    "Pos": [
      41099891581.0,
      -84533830294.0,
      0.0
    ],
    "Radius": 4
  },
  {
    "ID": 254,
    "Mass": 8.2109,
    "Name": "IMA2R7",
    "Pos": [
      68364622068.0,
      8467250326.0,
      0.0
    ],
    "Radius": 14
  },
  {
    "ID": 255,
    "Mass": 9.0637,
    "Name": "7BA968",
    "Pos": [
      92630884353.0,
      -4284098326.0,
      0.0
    ],
    "Radius": 10
  },
  {
    "ID": 256,
    "Mass": 7.49,
    "Name": "NGICVM",
    "Pos": [
      -80483547720.0,
      -72106684270.0,
      0.0
    ],
    "Radius": 5
  },
  {
    "ID": 257,
    "Mass": 7.352,
    "Name": "716CZA",
    "Pos": [
      -80049885341.0,
      -19306105323.0,
      0.0
    ],
    "Radius": 7
  },
  {
    "ID": 258,
    "Mass": 3.2387,
    "Name": "4XMB48",
    "Pos": [
      25184631670.0,
      78764920657.0,
      0.0
    ],
    "Radius": 20
  },
  {
    "ID": 259,
    "Mass": 9.8031,
    "Name": "X1YT8E",
    "Pos": [
      -21778357758.0,
      -41426972783.0,
      0.0
    ],
    "Radius": 19
  },
  {
    "ID": 260,
    "Mass": 2.6669,
    "Name": "8DLW5L",
    "Pos": [
      78127162890.0,
      -85840222511.0,
      0.0
    ],
    "Radius": 4
  },
  {
    "ID": 261,
    "Mass": 8.3098,
    "Name": "55G21S",
    "Pos": [
      43970522378.0,
      -52850611813.0,
      0.0
    ],
    "Radius": 20
  },
  {
    "ID": 262,
    "Mass": 4.5365,
    "Name": "BIHJVZ",
    "Pos": [
      35756332605.0,
      -19698590096.0,
      0.0
    ],
    "Radius": 14
  },
  {
    "ID": 263,
    "Mass": 1.9058,
    "Name": "IKZAJX",
    "Pos": [
      55788277667.0,
      84105071171.0,
      0.0
    ],
    "Radius": 21
  },
  {
    "ID": 264,
    "Mass": 3.4053,
    "Name": "H7HWJD",
    "Pos": [
      -95028555277.0,
      -52546994835.0,
      0.0
    ],
    "Radius": 12
  },
  {
    "ID": 265,
    "Mass": 6.328,
    "Name": "RZ25EN",
    "Pos": [
      41584701834.0,
      38938369444.0,
      0.0
    ],
    "Radius": 6
  },
  {
    "ID": 266,
    "Mass": 3.65,
    "Name": "EQOSZH",
    "Pos": [
      -90337544897.0,
      36873872143.0,
      0.0
    ],
    "Radius": 15
  },
  {
    "ID": 267,
    "Mass": 6.0967,
    "Name": "HFNYOG",
    "Pos": [
      -53187527418.0,
      -72613561787.0,
      0.0
    ],
    "Radius": 10
  },
  {
    "ID": 268,
    "Mass": 4.3424,
    "Name": "WDR2SK",
    "Pos": [
      64985440311.0,
      649242282.0,
      0.0
    ],
    "Radius": 19
  },
  {
    "ID": 269,
    "Mass": 3.6942,
    "Name": "XU0A5Q",
    "Pos": [
      -28541657343.0,
      -6088228803.0,
      0.0
    ],
    "Radius": 16
  },
  {
    "ID": 270,
    "Mass": 1.2276,
    "Name": "28B6E3",
    "Pos": [
      -34171372509.0,
      77020867186.0,
      0.0
    ],
    "Radius": 21
  },
  {
    "ID": 271,
    "Mass": 4.4208,
    "Name": "KNHV4L",
    "Pos": [
      29218467255.0,
      96809945502.0,
      0.0
    ],
    "Radius": 13
  },
  {
    "ID": 272,
    "Mass": 2.8047,
    "Name": "N2D45C",
    "Pos": [
      -54115041994.0,
      -67510822556.0,
      0.0
    ],
    "Radius": 19
  },
  {
    "ID": 273,
    "Mass": 1.843,
    "Name": "64I7CW",
    "Pos": [
      77621815015.0,
      64002571291.0,
      0.0
    ],
    "Radius": 14
  },
  {
    "ID": 274,
    "Mass": 6.3653,
    "Name": "VHBXYV",
    "Pos": [
      -95086514331.0,
      39682356785.0,
      0.0
    ],
    "Radius": 9
  },
  {
    "ID": 275,
    "Mass": 1.9972,
    "Name": "RGY9QV",
    "Pos": [
      -45394661297.0,
      4827070052.0,
      0.0
    ],
    "Radius": 22
  },
  {
    "ID": 276,
    "Mass": 3.518,
    "Name": "4L0LDE",
    "Pos": [
      -83016679759.0,
      -88171896697.0,
      0.0
    ],
    "Radius": 9
  },
  {
    "ID": 277,
    "Mass": 9.0134,
    "Name": "HA9EY7",
    "Pos": [
      88062819292.0,
      46080129979.0,
      0.0
    ],
    "Radius": 21
  },
  {
    "ID": 278,
    "Mass": 2.3935,
    "Name": "BJSE1T",
    "Pos": [
      39538793956.0,
      74488190104.0,
      0.0
    ],
    "Radius": 11
  },
  {
    "ID": 279,
    "Mass": 1.7503,
    "Name": "XSTQJP",
    "Pos": [
      56804001019.0,
      -92639112218.0,
      0.0
    ],
    "Radius": 23
  },
  {
    "ID": 280,
    "Mass": 3.478,
    "Name": "6HJ3PM",
    "Pos": [
      -2174276062.0,
      -11771609166.0,
      0.0
    ],
    "Radius": 15
  },
  {
    "ID": 281,
    "Mass": 5.6447,
    "Name": "G6UAVZ",
    "Pos": [
      8327131021.0,
      81428775380.0,
      0.0
    ],
    "Radius": 17
  },
  {
    "ID": 282,
    "Mass": 8.4613,
    "Name": "RI1A93",
    "Pos": [
      -44151269748.0,
      35839304269.0,
      0.0
    ],
    "Radius": 7
  },
  {
    "ID": 283,
    "Mass": 8.1922,
    "Name": "P7DVRN",
    "Pos": [
      26518422623.0,
      6229516537.0,
      0.0
    ],
    "Radius": 23
  },
  {
    "ID": 284,
    "Mass": 1.9805,
    "Name": "SXDTY3",
    "Pos": [
      67362857808.0,
      -50081415671.0,
      0.0
    ],
    "Radius": 7
  },
  {
    "ID": 285,
    "Mass": 6.559,
    "Name": "83KYHV",
    "Pos": [
      -19848176170.0,
      -1147329997.0,
      0.0
    ],
    "Radius": 18
  },
  {
    "ID": 286,
    "Mass": 7.2459,
    "Name": "560PZJ",
    "Pos": [
      60392090036.0,
      18284921623.0,
      0.0
    ],
    "Radius": 16
  },
  {
    "ID": 287,
    "Mass": 7.7255,
    "Name": "2OL40T",
    "Pos": [
      -7769074562.0,
      15852988443.0,
      0.0
    ],
    "Radius": 23
  },
  {
    "ID": 288,
    "Mass": 5.6975,
    "Name": "2CCR5K",
    "Pos": [
      -21617949381.0,
      18368351686.0,
      0.0
    ],
    "Radius": 5
  },
  {
    "ID": 289,
    "Mass": 9.0278,
    "Name": "BZMMXO",
    "Pos": [
      -29120719775.0,
      8030557907.0,
      0.0
    ],
    "Radius": 16
  },
  {
    "ID": 290,
    "Mass": 4.9911,
    "Name": "K1PPM9",
    "Pos": [
      -26004873877.0,
      99927869875.0,
      0.0
    ],
    "Radius": 22
  },
  {
    "ID": 291,
    "Mass": 8.6533,
    "Name": "CW8BQ2",
    "Pos": [
      -23221373283.0,
      30492163788.0,
      0.0
    ],
    "Radius": 11
  },
  {
    "ID": 292,
    "Mass": 5.5564,
    "Name": "0U7DR9",
    "Pos": [
      -53770198603.0,
      -35218642783.0,
      0.0
    ],
    "Radius": 12
  },
  {
    "ID": 293,
    "Mass": 7.1431,
    "Name": "CY8J8E",
    "Pos": [
      -98500956441.0,
      39290270683.0,
      0.0
    ],
    "Radius": 16
  },
  {
    "ID": 294,
    "Mass": 4.7018,
    "Name": "TOOMHN",
    "Pos": [
      17902593802.0,
      -16176352314.0,
      0.0
    ],
    "Radius": 15
  },
  {
    "ID": 295,
    "Mass": 3.962,
    "Name": "JCQ69W",
    "Pos": [
      -16451709422.0,
      -87263782810.0,
      0.0
    ],
    "Radius": 19
  },
  {
    "ID": 296,
    "Mass": 4.8491,
    "Name": "U3RC7J",
    "Pos": [
      -45871392262.0,
      30583809867.0,
      0.0
    ],
    "Radius": 22
  },
  {
    "ID": 297,
    "Mass": 2.2268,
    "Name": "ALSCQK",
    "Pos": [
      45636112368.0,
      -99032383826.0,
      0.0
    ],
    "Radius": 14
  },
  {
    "ID": 298,
    "Mass": 7.2157,
    "Name": "RTTACB",
    "Pos": [
      -65408107366.0,
      91026745716.0,
      0.0
    ],
    "Radius": 11
  },
  {
    "ID": 299,
    "Mass": 6.7485,
    "Name": "6FOK25",
    "Pos": [
      34880312434.0,
      88519424360.0,
      0.0
    ],
    "Radius": 22
  },
  {
    "ID": 300,
    "Mass": 9.5914,
    "Name": "WNHUK1",
    "Pos": [
      -35984056342.0,
      56836341759.0,
      0.0
    ],
    "Radius": 6
  },
  {
    "ID": 301,
    "Mass": 6.0659,
    "Name": "R4A4FU",
    "Pos": [
      80239008897.0,
      93803689672.0,
      0.0
    ],
    "Radius": 22
  },
  {
    "ID": 302,
    "Mass": 3.0645,
    "Name": "79RXDA",
    "Pos": [
      82493348586.0,
      36075284556.0,
      0.0
    ],
    "Radius": 6
  },
  {
    "ID": 303,
    "Mass": 7.6391,
    "Name": "HLZ74O",
    "Pos": [
      -27541480083.0,
      21681415416.0,
      0.0
    ],
    "Radius": 16
  },
  {
    "ID": 304,
    "Mass": 7.7647,
    "Name": "ZK7VXT",
    "Pos": [
      -15242043749.0,
      9621399561.0,
      0.0
    ],
    "Radius": 22
  },
  {
    "ID": 305,
    "Mass": 7.4422,
    "Name": "XTMG8C",
    "Pos": [
      -55496715162.0,
      77667218935.0,
      0.0
    ],
    "Radius": 23
  },
  {
    "ID": 306,
    "Mass": 7.0009,
    "Name": "UL6C0Q",
    "Pos": [
      -83833500948.0,
      24413961407.0,
      0.0
    ],
    "Radius": 15
  },
  {
    "ID": 307,
    "Mass": 5.3521,
    "Name": "I3VLK3",
    "Pos": [
      35997642236.0,
      -4054477393.0,
      0.0
    ],
    "Radius": 20
  },
  {
    "ID": 308,
    "Mass": 2.6366,
    "Name": "HUMELZ",
    "Pos": [
      3211981742.0,
      -71990484534.0,
      0.0
    ],
    "Radius": 7
  },
  {
    "ID": 309,
    "Mass": 1.0537,
    "Name": "05P8VK",
    "Pos": [
      -31818710398.0,
      -10363679122.0,
      0.0
    ],
    "Radius": 7
  },
  {
    "ID": 310,
    "Mass": 1.5785,
    "Name": "YFE3AR",
    "Pos": [
      -75147494327.0,
      -89957012357.0,
      0.0
    ],
    "Radius": 19
  },
  {
    "ID": 311,
    "Mass": 1.9196,
    "Name": "L87KSI",
    "Pos": [
      -8139043900.0,
      33049103220.0,
      0.0
    ],
    "Radius": 5
  },
  {
    "ID": 312,
    "Mass": 7.8863,
    "Name": "PI3MUC",
    "Pos": [
      -23178292618.0,
      41294982226.0,
      0.0
    ],
    "Radius": 12
  },
  {
    "ID": 313,
    "Mass": 8.8319,
    "Name": "SU5I9N",
    "Pos": [
      21215481848.0,
      90650624446.0,
      0.0
    ],
    "Radius": 12
  },
  {
    "ID": 314,
    "Mass": 8.1616,
    "Name": "PRMZAR",
    "Pos": [
      58880392799.0,
      -24087300279.0,
      0.0
    ],
    "Radius": 15
  },
  {
    "ID": 315,
    "Mass": 3.9006,
    "Name": "Z90FH4",
    "Pos": [
      56366988394.0,
      -21895447302.0,
      0.0
    ],
    "Radius": 4
  },
  {
    "ID": 316,
    "Mass": 6.9794,
    "Name": "LVL0VT",
    "Pos": [
      -27841952190.0,
      -32023296865.0,
      0.0
    ],
    "Radius": 5
  },
  {
    "ID": 317,
    "Mass": 7.9116,
    "Name": "6H0YRS",
    "Pos": [
      82327941197.0,
      -91415822648.0,
      0.0
    ],
    "Radius": 15
  },
  {
    "ID": 318,
    "Mass": 9.9271,
    "Name": "9YNTWY",
    "Pos": [
      3707016599.0,
      89409998067.0,
      0.0
    ],
    "Radius": 11
  },
  {
    "ID": 319,
    "Mass": 1.7426,
    "Name": "CBHGGY",
    "Pos": [
      55975885631.0,
      56050662477.0,
      0.0
    ],
    "Radius": 8
  },
  {
    "ID": 320,
    "Mass": 1.3063,
    "Name": "0GIR5M",
    "Pos": [
      45841620727.0,
      -11726164070.0,
      0.0
    ],
    "Radius": 11
  },
  {
    "ID": 321,
    "Mass": 2.9105,
    "Name": "ACXPX5",
    "Pos": [
      -17964930896.0,
      -64363391489.0,
      0.0
    ],
    "Radius": 11
  },
  {
    "ID": 322,
    "Mass": 7.8494,
    "Name": "WNMYFU",
    "Pos": [
      -61485790252.0,
      -22982703281.0,
      0.0
    ],
    "Radius": 19
  },
  {
    "ID": 323,
    "Mass": 5.1651,
    "Name": "SYUF7V",
    "Pos": [
      70957199884.0,
      16319583929.0,
      0.0
    ],
    "Radius": 8
  },
  {
    "ID": 324,
    "Mass": 5.2874,
    "Name": "7LRXS5",
    "Pos": [
      -89928767883.0,
      -69652934751.0,
      0.0
    ],
    "Radius": 4
  },
  {
    "ID": 325,
    "Mass": 5.2904,
    "Name": "3CTPMK",
    "Pos": [
      17770889098.0,
      67434964038.0,
      0.0
    ],
    "Radius": 17
  },
  {
    "ID": 326,
    "Mass": 9.3571,
    "Name": "OCBLWF",
    "Pos": [
      47986275246.0,
      80166193468.0,
      0.0
    ],
    "Radius": 18
  },
  {
    "ID": 327,
    "Mass": 2.1413,
    "Name": "2VDEKH",
    "Pos": [
      -93039079784.0,
      -7537868002.0,
      0.0
    ],
    "Radius": 17
  },
  {
    "ID": 328,
    "Mass": 4.8347,
    "Name": "PX53JG",
    "Pos": [
      -43350144568.0,
      -10514171772.0,
      0.0
    ],
    "Radius": 16
  },
  {
    "ID": 329,
    "Mass": 6.3991,
    "Name": "J0GN0L",
    "Pos": [
      -67327304656.0,
      -72541844079.0,
      0.0
    ],
    "Radius": 19
  },
  {
    "ID": 330,
    "Mass": 3.7001,
    "Name": "7R1GIB",
    "Pos": [
      67166027436.0,
      -90926971386.0,
      0.0
    ],
    "Radius": 7
  },
  {
    "ID": 331,
    "Mass": 5.7832,
    "Name": "VWKZ9D",
    "Pos": [
      47821947017.0,
      28513080515.0,
      0.0
    ],
    "Radius": 17
  },
  {
    "ID": 332,
    "Mass": 5.7115,
    "Name": "1U25NN",
    "Pos": [
      -54448224125.0,
      -67502033618.0,
      0.0
    ],
    "Radius": 10
  },
  {
    "ID": 333,
    "Mass": 6.2263,
    "Name": "AVS82A",
    "Pos": [
      45342359374.0,
      23764707458.0,
      0.0
    ],
    "Radius": 23
  },
  {
    "ID": 334,
    "Mass": 7.3932,
    "Name": "AFRPTS",
    "Pos": [
      90825310998.0,
      73336675721.0,
      0.0
    ],
    "Radius": 20
  },
  {
    "ID": 335,
    "Mass": 1.8118,
    "Name": "3JC9UM",
    "Pos": [
      99603595272.0,
      -91456082067.0,
      0.0
    ],
    "Radius": 16
  },
  {
    "ID": 336,
    "Mass": 7.5071,
    "Name": "9LTMZQ",
    "Pos": [
      86241861377.0,
      -10344548624.0,
      0.0
    ],
    "Radius": 14
  },
  {
    "ID": 337,
    "Mass": 5.1508,
    "Name": "20XT9U",
    "Pos": [
      85029077792.0,
      86619524171.0,
      0.0
    ],
    "Radius": 5
  },
  {
    "ID": 338,
    "Mass": 8.6247,
    "Name": "ANC2ND",
    "Pos": [
      47303065086.0,
      -41692064824.0,
      0.0
    ],
    "Radius": 14
  },
  {
    "ID": 339,
    "Mass": 9.1714,
    "Name": "QVNT7X",
    "Pos": [
      -58685341454.0,
      -23368179448.0,
      0.0
    ],
    "Radius": 7
  },
  {
    "ID": 340,
    "Mass": 7.7772,
    "Name": "CA3DVR",
    "Pos": [
      -33208971268.0,
      -91899007829.0,
      0.0
    ],
    "Radius": 12
  },
  {
    "ID": 341,
    "Mass": 1.4375,
    "Name": "8FCTKE",
    "Pos": [
      70900281933.0,
      -86774574968.0,
      0.0
    ],
    "Radius": 18
  },
  {
    "ID": 342,
    "Mass": 9.4643,
    "Name": "2CQZZ2",
    "Pos": [
      -55852526363.0,
      -50782976807.0,
      0.0
    ],
    "Radius": 6
  },
  {
    "ID": 343,
    "Mass": 3.9551,
    "Name": "GJT2C5",
    "Pos": [
      -14039239821.0,
      10428126610.0,
      0.0
    ],
    "Radius": 18
  },
  {
    "ID": 344,
    "Mass": 9.1117,
    "Name": "OFMG5S",
    "Pos": [
      -29296434469.0,
      10547788082.0,
      0.0
    ],
    "Radius": 10
  },
  {
    "ID": 345,
    "Mass": 9.3051,
    "Name": "MA489Q",
    "Pos": [
      -78344201030.0,
      -83927208654.0,
      0.0
    ],
    "Radius": 20
  },
  {
    "ID": 346,
    "Mass": 8.3832,
    "Name": "LJ20X4",
    "Pos": [
      -39342523101.0,
      -30628510431.0,
      0.0
    ],
    "Radius": 15
  },
  {
    "ID": 347,
    "Mass": 2.6193,
    "Name": "CS3W3E",
    "Pos": [
      38392740588.0,
      -43526082483.0,
      0.0
    ],
    "Radius": 13
  },
  {
    "ID": 348,
    "Mass": 7.2971,
    "Name": "RZIZRQ",
    "Pos": [
      -14169842442.0,
      21869188364.0,
      0.0
    ],
    "Radius": 5
  },
  {
    "ID": 349,
    "Mass": 4.617,
    "Name": "JTHGOX",
    "Pos": [
      30806403949.0,
      -78046900667.0,
      0.0
    ],
    "Radius": 13
  },
  {
    "ID": 350,
    "Mass": 9.9277,
    "Name": "YOH4R1",
    "Pos": [
      -53719457336.0,
      97587469888.0,
      0.0
    ],
    "Radius": 18
  },
  {
    "ID": 351,
    "Mass": 1.9183,
    "Name": "TLZRM1",
    "Pos": [
      -45577740469.0,
      44489365462.0,
      0.0
    ],
    "Radius": 9
  },
  {
    "ID": 352,
    "Mass": 6.9924,
    "Name": "1XAZIO",
    "Pos": [
      -95674001658.0,
      66732331017.0,
      0.0
    ],
    "Radius": 15
  },
  {
    "ID": 353,
    "Mass": 4.9632,
    "Name": "4SF7KM",
    "Pos": [
      11014853016.0,
      -70328338249.0,
      0.0
    ],
    "Radius": 12
  },
  {
    "ID": 354,
    "Mass": 9.9576,
    "Name": "W9FYMQ",
    "Pos": [
      -23825795322.0,
      67689564031.0,
      0.0
    ],
    "Radius": 20
  },
  {
    "ID": 355,
    "Mass": 1.9429,
    "Name": "WBQUQB",
    "Pos": [
      -85054756369.0,
      -94636418443.0,
      0.0
    ],
    "Radius": 20
  },
  {
    "ID": 356,
    "Mass": 3.5906,
    "Name": "76GU7W",
    "Pos": [
      -4897544483.0,
      47241383981.0,
      0.0
    ],
    "Radius": 12
  },
  {
    "ID": 357,
    "Mass": 1.8789,
    "Name": "JC39DL",
    "Pos": [
      -83748271667.0,
      -49897043962.0,
      0.0
    ],
    "Radius": 17
  },
  {
    "ID": 358,
    "Mass": 2.9589,
    "Name": "W0X3YK",
    "Pos": [
      27445301711.0,
      88257711525.0,
      0.0
    ],
    "Radius": 13
  },
  {
    "ID": 359,
    "Mass": 3.5144,
    "Name": "E6EGQ1",
    "Pos": [
      -54916959494.0,
      72677615449.0,
      0.0
    ],
    "Radius": 20
  },
  {
    "ID": 360,
    "Mass": 4.4895,
    "Name": "Z5TCT3",
    "Pos": [
      -52359936629.0,
      -83273632996.0,
      0.0
    ],
    "Radius": 16
  },
  {
    "ID": 361,
    "Mass": 1.0691,
    "Name": "VK6LZI",
    "Pos": [
      -73026112845.0,
      -16811775812.0,
      0.0
    ],
    "Radius": 22
  },
  {
    "ID": 362,
    "Mass": 7.154,
    "Name": "ERT7BX",
    "Pos": [
      -88137954359.0,
      50448047601.0,
      0.0
    ],
    "Radius": 20
  },
  {
    "ID": 363,
    "Mass": 1.618,
    "Name": "OLG105",
    "Pos": [
      27052931593.0,
      34133593054.0,
      0.0
    ],
    "Radius": 22
  },
  {
    "ID": 364,
    "Mass": 3.1058,
    "Name": "E6WIVO",
    "Pos": [
      -25140126995.0,
      -83508265614.0,
      0.0
    ],
    "Radius": 14
  },
  {
    "ID": 365,
    "Mass": 4.5923,
    "Name": "NM4JB5",
    "Pos": [
      -66317827994.0,
      -91899329670.0,
      0.0
    ],
    "Radius": 15
  },
  {
    "ID": 366,
    "Mass": 9.908,
    "Name": "MQALFM",
    "Pos": [
      38901774966.0,
      -10523337316.0,
      0.0
    ],
    "Radius": 12
  },
  {
    "ID": 367,
    "Mass": 6.2348,
    "Name": "7ZQC68",
    "Pos": [
      43650464630.0,
      -44981549785.0,
      0.0
    ],
    "Radius": 22
  },
  {
    "ID": 368,
    "Mass": 7.8684,
    "Name": "ESQN6M",
    "Pos": [
      -67731282146.0,
      45760875334.0,
      0.0
    ],
    "Radius": 23
  },
  {
    "ID": 369,
    "Mass": 7.5232,
    "Name": "AU9XBV",
    "Pos": [
      79504296123.0,
      72023817183.0,
      0.0
    ],
    "Radius": 6
  },
  {
    "ID": 370,
    "Mass": 2.4133,
    "Name": "E66090",
    "Pos": [
      -58058614450.0,
      84967381610.0,
      0.0
    ],
    "Radius": 15
  },
  {
    "ID": 371,
    "Mass": 8.3288,
    "Name": "I3EG44",
    "Pos": [
      -57549206922.0,
      34998138378.0,
      0.0
    ],
    "Radius": 5
  },
  {
    "ID": 372,
    "Mass": 8.5015,
    "Name": "7MQUEY",
    "Pos": [
      -45575305276.0,
      25114760193.0,
      0.0
    ],
    "Radius": 8
  },
  {
    "ID": 373,
    "Mass": 1.2024,
    "Name": "N8ZKI6",
    "Pos": [
      -88601270082.0,
      -16615414845.0,
      0.0
    ],
    "Radius": 19
  },
  {
    "ID": 374,
    "Mass": 8.4389,
    "Name": "SAPL7Q",
    "Pos": [
      -43812632976.0,
      88236071211.0,
      0.0
    ],
    "Radius": 19
  },
  {
    "ID": 375,
    "Mass": 1.8433,
    "Name": "JCT1QP",
    "Pos": [
      64163564912.0,
      -60774004664.0,
      0.0
    ],
    "Radius": 23
  },
  {
    "ID": 376,
    "Mass": 2.9543,
    "Name": "OXQG31",
    "Pos": [
      45464945460.0,
      86582741941.0,
      0.0
    ],
    "Radius": 13
  },
  {
    "ID": 377,
    "Mass": 7.3518,
    "Name": "KDTU1X",
    "Pos": [
      16384681194.0,
      -63713318389.0,
      0.0
    ],
    "Radius": 5
  },
  {
    "ID": 378,
    "Mass": 3.585,
    "Name": "GNA171",
    "Pos": [
      -47907690851.0,
      -86917050502.0,
      0.0
    ],
    "Radius": 6
  },
  {
    "ID": 379,
    "Mass": 8.3728,
    "Name": "RHWQEI",
    "Pos": [
      -43543847050.0,
      99491586303.0,
      0.0
    ],
    "Radius": 17
  },
  {
    "ID": 380,
    "Mass": 3.7049,
    "Name": "O470Y0",
    "Pos": [
      -1996153907.0,
      -50162017985.0,
      0.0
    ],
    "Radius": 19
  },
  {
    "ID": 381,
    "Mass": 8.491,
    "Name": "5JG7FL",
    "Pos": [
      -42759378074.0,
      93465754746.0,
      0.0
    ],
    "Radius": 15
  },
  {
    "ID": 382,
    "Mass": 2.9267,
    "Name": "TTEWQV",
    "Pos": [
      54309204954.0,
      -89780396190.0,
      0.0
    ],
    "Radius": 17
  },
  {
    "ID": 383,
    "Mass": 8.7486,
    "Name": "TDNPJ4",
    "Pos": [
      15873712567.0,
      69280690385.0,
      0.0
    ],
    "Radius": 7
  },
  {
    "ID": 384,
    "Mass": 2.2207,
    "Name": "S8I8BH",
    "Pos": [
      83136758784.0,
      91006098059.0,
      0.0
    ],
    "Radius": 8
  },
  {
    "ID": 385,
    "Mass": 4.7711,
    "Name": "A80L4D",
    "Pos": [
      23819354736.0,
      -40152067205.0,
      0.0
    ],
    "Radius": 13
  },
  {
    "ID": 386,
    "Mass": 6.0065,
    "Name": "X8P000",
    "Pos": [
      -71020079409.0,
      -72980553133.0,
      0.0
    ],
    "Radius": 7
  },
  {
    "ID": 387,
    "Mass": 3.7717,
    "Name": "IPUUOZ",
    "Pos": [
      67225190027.0,
      59008125129.0,
      0.0
    ],
    "Radius": 19
  },
  {
    "ID": 388,
    "Mass": 8.4964,
    "Name": "LD7TO8",
    "Pos": [
      59904010815.0,
      41449283630.0,
      0.0
    ],
    "Radius": 19
  },
  {
    "ID": 389,
    "Mass": 2.7596,
    "Name": "F2A1E6",
    "Pos": [
      83256786296.0,
      -5177017872.0,
      0.0
    ],
    "Radius": 10
  },
  {
    "ID": 390,
    "Mass": 8.7762,
    "Name": "5B4E48",
    "Pos": [
      -21624561098.0,
      -49366036417.0,
      0.0
    ],
    "Radius": 15
  },
  {
    "ID": 391,
    "Mass": 2.094,
    "Name": "KV2HA4",
    "Pos": [
      11338894636.0,
      7615210489.0,
      0.0
    ],
    "Radius": 14
  },
  {
    "ID": 392,
    "Mass": 7.3651,
    "Name": "E3KJSF",
    "Pos": [
      74025475246.0,
      -78350781007.0,
      0.0
    ],
    "Radius": 19
  },
  {
    "ID": 393,
    "Mass": 1.3848,
    "Name": "KU67SX",
    "Pos": [
      623226915.0,
      -54550955185.0,
      0.0
    ],
    "Radius": 21
  },
  {
    "ID": 394,
    "Mass": 3.5585,
    "Name": "U9IEJQ",
    "Pos": [
      -27373803231.0,
      -85788305711.0,
      0.0
    ],
    "Radius": 22
  },
  {
    "ID": 395,
    "Mass": 6.4138,
    "Name": "OX0QN2",
    "Pos": [
      -25085281885.0,
      -79778863398.0,
      0.0
    ],
    "Radius": 8
  },
  {
    "ID": 396,
    "Mass": 5.9091,
    "Name": "3V4MHD",
    "Pos": [
      -49180458932.0,
      73198893917.0,
      0.0
    ],
    "Radius": 14
  },
  {
    "ID": 397,
    "Mass": 7.9604,
    "Name": "CSMG1Q",
    "Pos": [
      -75309449563.0,
      7738805683.0,
      0.0
    ],
    "Radius": 12
  },
  {
    "ID": 398,
    "Mass": 3.3551,
    "Name": "AWHLZ5",
    "Pos": [
      -80305220767.0,
      -51625669780.0,
      0.0
    ],
    "Radius": 7
  },
  {
    "ID": 399,
    "Mass": 8.3538,
    "Name": "I77OVR",
    "Pos": [
      87062559430.0,
      -21780528680.0,
      0.0
    ],
    "Radius": 21
  },
  {
    "ID": 400,
    "Mass": 4.4019,
    "Name": "MBOSNL",
    "Pos": [
      -86303667856.0,
      30868766320.0,
      0.0
    ],
    "Radius": 11
  },
  {
    "ID": 401,
    "Mass": 1.7207,
    "Name": "HIXFCF",
    "Pos": [
      45165064745.0,
      23154028167.0,
      0.0
    ],
    "Radius": 15
  },
  {
    "ID": 402,
    "Mass": 7.7182,
    "Name": "BKK1FQ",
    "Pos": [
      -19693421926.0,
      40610332485.0,
      0.0
    ],
    "Radius": 16
  },
  {
    "ID": 403,
    "Mass": 8.7584,
    "Name": "055G8P",
    "Pos": [
      13247587338.0,
      -62284197687.0,
      0.0
    ],
    "Radius": 11
  },
  {
    "ID": 404,
    "Mass": 2.0351,
    "Name": "JQRSVO",
    "Pos": [
      58881242197.0,
      69777101672.0,
      0.0
    ],
    "Radius": 17
  },
  {
    "ID": 405,
    "Mass": 6.1905,
    "Name": "DU9NC8",
    "Pos": [
      -29828750446.0,
      -29577113987.0,
      0.0
    ],
    "Radius": 6
  },
  {
    "ID": 406,
    "Mass": 7.4235,
    "Name": "8L1DCX",
    "Pos": [
      -19201977085.0,
      88706508867.0,
      0.0
    ],
    "Radius": 9
  },
  {
    "ID": 407,
    "Mass": 7.964,
    "Name": "8O6DXK",
    "Pos": [
      -89755424645.0,
      39696534553.0,
      0.0
    ],
    "Radius": 7
  },
  {
    "ID": 408,
    "Mass": 1.9379,
    "Name": "W0KNNG",
    "Pos": [
      85360415357.0,
      -46395154343.0,
      0.0
    ],
    "Radius": 19
  },
  {
    "ID": 409,
    "Mass": 1.6353,
    "Name": "BYMEFI",
    "Pos": [
      92144547491.0,
      -41556741324.0,
      0.0
    ],
    "Radius": 5
  },
  {
    "ID": 410,
    "Mass": 8.6568,
    "Name": "995QKS",
    "Pos": [
      -96657583094.0,
      84945032746.0,
      0.0
    ],
    "Radius": 14
  },
  {
    "ID": 411,
    "Mass": 5.3284,
    "Name": "UQVKEN",
    "Pos": [
      55204390313.0,
      -64859862100.0,
      0.0
    ],
    "Radius": 22
  },
  {
    "ID": 412,
    "Mass": 7.6379,
    "Name": "00V4RA",
    "Pos": [
      -58484528214.0,
      -83186338922.0,
      0.0
    ],
    "Radius": 9
  },
  {
    "ID": 413,
    "Mass": 7.8906,
    "Name": "E0A7ND",
    "Pos": [
      -72093546731.0,
      -26266873191.0,
      0.0
    ],
    "Radius": 14
  },
  {
    "ID": 414,
    "Mass": 5.3335,
    "Name": "1DP6TL",
    "Pos": [
      -94769746364.0,
      -46882977453.0,
      0.0
    ],
    "Radius": 7
  },
  {
    "ID": 415,
    "Mass": 8.1433,
    "Name": "O5Q9RW",
    "Pos": [
      53085741634.0,
      -25564857496.0,
      0.0
    ],
    "Radius": 18
  },
  {
    "ID": 416,
    "Mass": 4.6079,
    "Name": "E9ZOO1",
    "Pos": [
      1093485049.0,
      52235768279.0,
      0.0
    ],
    "Radius": 20
  },
  {
    "ID": 417,
    "Mass": 3.0188,
    "Name": "3SMBYS",
    "Pos": [
      -51830676357.0,
      -71489969888.0,
      0.0
    ],
    "Radius": 10
  },
  {
    "ID": 418,
    "Mass": 4.5994,
    "Name": "3H4BPT",
    "Pos": [
      46489551402.0,
      56542169421.0,
      0.0
    ],
    "Radius": 16
  },
  {
    "ID": 419,
    "Mass": 4.4745,
    "Name": "LY9Q6U",
    "Pos": [
      -47933757127.0,
      -76192594134.0,
      0.0
    ],
    "Radius": 23
  },
  {
    "ID": 420,
    "Mass": 9.3522,
    "Name": "IFIBK4",
    "Pos": [
      -7516806398.0,
      74818373933.0,
      0.0
    ],
    "Radius": 8
  },
  {
    "ID": 421,
    "Mass": 3.7764,
    "Name": "D197IQ",
    "Pos": [
      -8695111630.0,
      -81129796773.0,
      0.0
    ],
    "Radius": 10
  },
  {
    "ID": 422,
    "Mass": 6.6227,
    "Name": "ED6NTB",
    "Pos": [
      -95822950662.0,
      -73170554335.0,
      0.0
    ],
    "Radius": 18
  },
  {
    "ID": 423,
    "Mass": 4.0266,
    "Name": "Y9Q1JH",
    "Pos": [
      52234576201.0,
      45940167470.0,
      0.0
    ],
    "Radius": 13
  },
  {
    "ID": 424,
    "Mass": 5.2896,
    "Name": "HGELAN",
    "Pos": [
      26971533804.0,
      -5575481692.0,
      0.0
    ],
    "Radius": 22
  },
  {
    "ID": 425,
    "Mass": 8.098,
    "Name": "2YCVW1",
    "Pos": [
      51659825789.0,
      79098434911.0,
      0.0
    ],
    "Radius": 18
  },
  {
    "ID": 426,
    "Mass": 8.0071,
    "Name": "VJS70P",
    "Pos": [
      -85159986745.0,
      83235143767.0,
      0.0
    ],
    "Radius": 23
  },
  {
    "ID": 427,
    "Mass": 1.8975,
    "Name": "L75OX2",
    "Pos": [
      -31188240086.0,
      93683545091.0,
      0.0
    ],
    "Radius": 14
  },
  {
    "ID": 428,
    "Mass": 8.4445,
    "Name": "SNVWGP",
    "Pos": [
      34834754393.0,
      -58528458110.0,
      0.0
    ],
    "Radius": 18
  },
  {
    "ID": 429,
    "Mass": 3.5317,
    "Name": "3V1YEQ",
    "Pos": [
      32223702299.0,
      92578176916.0,
      0.0
    ],
    "Radius": 11
  },
  {
    "ID": 430,
    "Mass": 3.9133,
    "Name": "MMNQB9",
    "Pos": [
      99282360676.0,
      -12669486973.0,
      0.0
    ],
    "Radius": 18
  },
  {
    "ID": 431,
    "Mass": 4.3722,
    "Name": "68207P",
    "Pos": [
      -16731636813.0,
      10214186173.0,
      0.0
    ],
    "Radius": 14
  },
  {
    "ID": 432,
    "Mass": 6.7545,
    "Name": "C93PL6",
    "Pos": [
      -83007085328.0,
      76197485933.0,
      0.0
    ],
    "Radius": 22
  },
  {
    "ID": 433,
    "Mass": 3.615,
    "Name": "ABYUFC",
    "Pos": [
      71957498383.0,
      90602511165.0,
      0.0
    ],
    "Radius": 23
  },
  {
    "ID": 434,
    "Mass": 3.7313,
    "Name": "SK0RUQ",
    "Pos": [
      -59080360208.0,
      -8446204859.0,
      0.0
    ],
    "Radius": 20
  },
  {
    "ID": 435,
    "Mass": 9.411,
    "Name": "0BYFS9",
    "Pos": [
      -79705537068.0,
      85814462877.0,
      0.0
    ],
    "Radius": 15
  },
  {
    "ID": 436,
    "Mass": 2.8415,
    "Name": "RJAOWD",
    "Pos": [
      58232101617.0,
      -32335485370.0,
      0.0
    ],
    "Radius": 17
  },
  {
    "ID": 437,
    "Mass": 4.9882,
    "Name": "408F2G",
    "Pos": [
      -22439273233.0,
      -52320726719.0,
      0.0
    ],
    "Radius": 14
  },
  {
    "ID": 438,
    "Mass": 1.977,
    "Name": "CCEOGF",
    "Pos": [
      15396542221.0,
      -28581379951.0,
      0.0
    ],
    "Radius": 21
  },
  {
    "ID": 439,
    "Mass": 2.2992,
    "Name": "XCNB4S",
    "Pos": [
      -93664701641.0,
      -33046098264.0,
      0.0
    ],
    "Radius": 22
  },
  {
    "ID": 440,
    "Mass": 9.8776,
    "Name": "4SZMCL",
    "Pos": [
      47576759032.0,
      1285239313.0,
      0.0
    ],
    "Radius": 10
  },
  {
    "ID": 441,
    "Mass": 5.3613,
    "Name": "88K1G8",
    "Pos": [
      -44053197754.0,
      -57596466909.0,
      0.0
    ],
    "Radius": 9
  },
  {
    "ID": 442,
    "Mass": 3.6692,
    "Name": "DFI7JR",
    "Pos": [
      6708271880.0,
      89662010867.0,
      0.0
    ],
    "Radius": 10
  },
  {
    "ID": 443,
    "Mass": 7.5036,
    "Name": "XWIVSW",
    "Pos": [
      -15265552804.0,
      47691778518.0,
      0.0
    ],
    "Radius": 12
  },
  {
    "ID": 444,
    "Mass": 1.6352,
    "Name": "3W6M1X",
    "Pos": [
      -56263967505.0,
      -48475515059.0,
      0.0
    ],
    "Radius": 22
  },
  {
    "ID": 445,
    "Mass": 9.045,
    "Name": "JUCA77",
    "Pos": [
      674194243.0,
      -32882776999.0,
      0.0
    ],
    "Radius": 7
  },
  {
    "ID": 446,
    "Mass": 3.4013,
    "Name": "L744HM",
    "Pos": [
      -84349701318.0,
      59082554.0,
      0.0
    ],
    "Radius": 14
  },
  {
    "ID": 447,
    "Mass": 4.7584,
    "Name": "75R05E",
    "Pos": [
      7173670924.0,
      -13020032489.0,
      0.0
    ],
    "Radius": 16
  },
  {
    "ID": 448,
    "Mass": 3.3221,
    "Name": "AXZRAI",
    "Pos": [
      -69298063769.0,
      -81645716919.0,
      0.0
    ],
    "Radius": 4
  },
  {
    "ID": 449,
    "Mass": 9.0215,
    "Name": "SJUT5K",
    "Pos": [
      36152680336.0,
      64297777940.0,
      0.0
    ],
    "Radius": 5
  },
  {
    "ID": 450,
    "Mass": 1.7526,
    "Name": "7YAE7G",
    "Pos": [
      32841924120.0,
      -71427356741.0,
      0.0
    ],
    "Radius": 8
  },
  {
    "ID": 451,
    "Mass": 3.7951,
    "Name": "WEVU9O",
    "Pos": [
      -83854644188.0,
      73232565035.0,
      0.0
    ],
    "Radius": 12
  },
  {
    "ID": 452,
    "Mass": 4.1297,
    "Name": "VBR2YV",
    "Pos": [
      29225654633.0,
      49183877317.0,
      0.0
    ],
    "Radius": 21
  },
  {
    "ID": 453,
    "Mass": 6.2883,
    "Name": "SPK7ZI",
    "Pos": [
      76867642763.0,
      84070589941.0,
      0.0
    ],
    "Radius": 16
  },
  {
    "ID": 454,
    "Mass": 7.6627,
    "Name": "POANOV",
    "Pos": [
      -31908035432.0,
      13605121791.0,
      0.0
    ],
    "Radius": 23
  },
  {
    "ID": 455,
    "Mass": 2.0943,
    "Name": "XQ0T4X",
    "Pos": [
      -40489427181.0,
      -51046733216.0,
      0.0
    ],
    "Radius": 6
  },
  {
    "ID": 456,
    "Mass": 4.9894,
    "Name": "92KXFZ",
    "Pos": [
      -34117311132.0,
      -29392374119.0,
      0.0
    ],
    "Radius": 4
  },
  {
    "ID": 457,
    "Mass": 4.2853,
    "Name": "HB6DAB",
    "Pos": [
      -95255284284.0,
      -36022558632.0,
      0.0
    ],
    "Radius": 4
  },
  {
    "ID": 458,
    "Mass": 2.0646,
    "Name": "W8CGPP",
    "Pos": [
      3596855395.0,
      78886507666.0,
      0.0
    ],
    "Radius": 7
  },
  {
    "ID": 459,
    "Mass": 6.3322,
    "Name": "KBWQ38",
    "Pos": [
      43286271563.0,
      -12408546228.0,
      0.0
    ],
    "Radius": 23
  },
  {
    "ID": 460,
    "Mass": 9.4586,
    "Name": "D1USFI",
    "Pos": [
      89018391945.0,
      -96883065144.0,
      0.0
    ],
    "Radius": 14
  },
  {
    "ID": 461,
    "Mass": 9.3786,
    "Name": "NW6GA3",
    "Pos": [
      88627023501.0,
      15424928078.0,
      0.0
    ],
    "Radius": 16
  },
  {
    "ID": 462,
    "Mass": 7.6932,
    "Name": "YE5U5U",
    "Pos": [
      -6325668790.0,
      79881331586.0,
      0.0
    ],
    "Radius": 17
  },
  {
    "ID": 463,
    "Mass": 3.5443,
    "Name": "HMC5RP",
    "Pos": [
      -7994544564.0,
      -90297777259.0,
      0.0
    ],
    "Radius": 15
  },
  {
    "ID": 464,
    "Mass": 3.291,
    "Name": "G7E98L",
    "Pos": [
      -98941155875.0,
      -74318853755.0,
      0.0
    ],
    "Radius": 9
  },
  {
    "ID": 465,
    "Mass": 8.3776,
    "Name": "37VJ2A",
    "Pos": [
      54612570285.0,
      -92077895268.0,
      0.0
    ],
    "Radius": 5
  },
  {
    "ID": 466,
    "Mass": 2.642,
    "Name": "N5KC66",
    "Pos": [
      -85347554979.0,
      -38000567903.0,
      0.0
    ],
    "Radius": 23
  },
  {
    "ID": 467,
    "Mass": 4.102,
    "Name": "DRF2KS",
    "Pos": [
      -38087732251.0,
      -88859798028.0,
      0.0
    ],
    "Radius": 13
  },
  {
    "ID": 468,
    "Mass": 7.3051,
    "Name": "MAJTOT",
    "Pos": [
      -65011182744.0,
      -20438037817.0,
      0.0
    ],
    "Radius": 9
  },
  {
    "ID": 469,
    "Mass": 9.7874,
    "Name": "YPU9YQ",
    "Pos": [
      3926237265.0,
      -40086893259.0,
      0.0
    ],
    "Radius": 17
  },
  {
    "ID": 470,
    "Mass": 7.36,
    "Name": "1JE9FH",
    "Pos": [
      -876039967.0,
      27946491196.0,
      0.0
    ],
    "Radius": 17
  },
  {
    "ID": 471,
    "Mass": 7.2062,
    "Name": "6L3FCU",
    "Pos": [
      43025088446.0,
      -52233453186.0,
      0.0
    ],
    "Radius": 20
  },
  {
    "ID": 472,
    "Mass": 3.107,
    "Name": "0C4QW3",
    "Pos": [
      -3468516097.0,
      40443039769.0,
      0.0
    ],
    "Radius": 16
  },
  {
    "ID": 473,
    "Mass": 9.4156,
    "Name": "KW7A83",
    "Pos": [
      76576373383.0,
      61499547978.0,
      0.0
    ],
    "Radius": 15
  },
  {
    "ID": 474,
    "Mass": 1.1853,
    "Name": "BDRJNB",
    "Pos": [
      73153791482.0,
      -67577061154.0,
      0.0
    ],
    "Radius": 19
  },
  {
    "ID": 475,
    "Mass": 5.2254,
    "Name": "7ARV31",
    "Pos": [
      -10386811704.0,
      48817875140.0,
      0.0
    ],
    "Radius": 13
  },
  {
    "ID": 476,
    "Mass": 3.4249,
    "Name": "RV4QYB",
    "Pos": [
      64707125569.0,
      54050741739.0,
      0.0
    ],
    "Radius": 22
  },
  {
    "ID": 477,
    "Mass": 9.3744,
    "Name": "O5VA40",
    "Pos": [
      -31576380428.0,
      15909295227.0,
      0.0
    ],
    "Radius": 20
  },
  {
    "ID": 478,
    "Mass": 3.9297,
    "Name": "3JYDP8",
    "Pos": [
      97430264156.0,
      88186615023.0,
      0.0
    ],
    "Radius": 12
  },
  {
    "ID": 479,
    "Mass": 9.5726,
    "Name": "E245QV",
    "Pos": [
      -76336875739.0,
      77425387087.0,
      0.0
    ],
    "Radius": 11
  },
  {
    "ID": 480,
    "Mass": 9.7386,
    "Name": "92JRQ4",
    "Pos": [
      -55705227529.0,
      -88027880823.0,
      0.0
    ],
    "Radius": 8
  },
  {
    "ID": 481,
    "Mass": 8.5083,
    "Name": "G72G2X",
    "Pos": [
      82359584646.0,
      -52621737199.0,
      0.0
    ],
    "Radius": 22
  },
  {
    "ID": 482,
    "Mass": 3.328,
    "Name": "L1R9MX",
    "Pos": [
      90473231182.0,
      -19926786523.0,
      0.0
    ],
    "Radius": 6
  },
  {
    "ID": 483,
    "Mass": 9.2175,
    "Name": "L0OI7G",
    "Pos": [
      89050015038.0,
      55381544038.0,
      0.0
    ],
    "Radius": 12
  },
  {
    "ID": 484,
    "Mass": 2.3224,
    "Name": "PONABP",
    "Pos": [
      80140000524.0,
      -72051566140.0,
      0.0
    ],
    "Radius": 12
  },
  {
    "ID": 485,
    "Mass": 4.3116,
    "Name": "JZ1V6J",
    "Pos": [
      -59369950824.0,
      51314421957.0,
      0.0
    ],
    "Radius": 13
  },
  {
    "ID": 486,
    "Mass": 3.3106,
    "Name": "2LJ43K",
    "Pos": [
      -58385143236.0,
      92244998773.0,
      0.0
    ],
    "Radius": 14
  },
  {
    "ID": 487,
    "Mass": 7.1265,
    "Name": "878J3D",
    "Pos": [
      -26283440373.0,
      86535522366.0,
      0.0
    ],
    "Radius": 8
  },
  {
    "ID": 488,
    "Mass": 8.5995,
    "Name": "JOMTHS",
    "Pos": [
      51946518802.0,
      -21293368054.0,
      0.0
    ],
    "Radius": 10
  },
  {
    "ID": 489,
    "Mass": 4.6568,
    "Name": "SXECHE",
    "Pos": [
      -51499912950.0,
      61728858296.0,
      0.0
    ],
    "Radius": 4
  },
  {
    "ID": 490,
    "Mass": 6.3784,
    "Name": "VBNKO4",
    "Pos": [
      4602997081.0,
      51485338062.0,
      0.0
    ],
    "Radius": 13
  },
  {
    "ID": 491,
    "Mass": 5.6267,
    "Name": "I2ZMDX",
    "Pos": [
      28669270856.0,
      19571559502.0,
      0.0
    ],
    "Radius": 14
  },
  {
    "ID": 492,
    "Mass": 4.4449,
    "Name": "3KP677",
    "Pos": [
      73804494878.0,
      -95522973319.0,
      0.0
    ],
    "Radius": 17
  },
  {
    "ID": 493,
    "Mass": 9.5513,
    "Name": "GONNU7",
    "Pos": [
      79370980997.0,
      -69988762059.0,
      0.0
    ],
    "Radius": 19
  },
  {
    "ID": 494,
    "Mass": 1.2338,
    "Name": "DOWFPY",
    "Pos": [
      -4442158186.0,
      -5080937956.0,
      0.0
    ],
    "Radius": 6
  },
  {
    "ID": 495,
    "Mass": 2.8516,
    "Name": "P84YIL",
    "Pos": [
      -22802011575.0,
      -136347092.0,
      0.0
    ],
    "Radius": 13
  },
  {
    "ID": 496,
    "Mass": 4.1847,
    "Name": "S87L1J",
    "Pos": [
      -17668792654.0,
      78100140804.0,
      0.0
    ],
    "Radius": 22
  },
  {
    "ID": 497,
    "Mass": 6.9897,
    "Name": "CEWYNE",
    "Pos": [
      54845284780.0,
      11919483365.0,
      0.0
    ],
    "Radius": 22
  },
  {
    "ID": 498,
    "Mass": 3.2464,
    "Name": "RWHDL1",
    "Pos": [
      -34486799202.0,
      -62513201405.0,
      0.0
    ],
    "Radius": 12
  },
  {
    "ID": 499,
    "Mass": 7.957,
    "Name": "50831F",
    "Pos": [
      83707044069.0,
      -45349042905.0,
      0.0
    ],
    "Radius": 4
  },
  {
    "ID": 500,
    "Mass": 6.1339,
    "Name": "HCSZWC",
    "Pos": [
      -48521505901.0,
      -49524546862.0,
      0.0
    ],
    "Radius": 17
  }
]